Workbook

Sheet Read Me
B6: Wilkins Media - Military On-Base Advertising Rate Card (MASTER)
B7: Generated September 29, 2026 from the standardized rate card (data/rate_card.csv).
B9: What this is | C9: One row per media option on each installation, with the VENDOR (base) cost at 1 / 3 / 6 / 12 months and production. Client prices are formulas driven by the Settings tab, so changing the margin re-prices every line.
B10: Source | C10: Box > Military > Master Grid > "MasterMilitaryOnBaseList 12.2.25 NS.xlsx", cleaned and normalized. Base populations are reference values from "Military - National Digital Inventory Master 6.3.26.xlsx".
B11: How to update a price | C11: Edit the Vendor Cost cells on the Rate Card tab. Put the year of the rate card you used in "Rate Card Year" and today's date in "Last Updated". Do not type into the Client Price columns - they are formulas.
B12: How to add a base or option | C12: Add a row at the bottom of the Rate Card table (the table extends automatically). Fill Base, State, DMA, Branch, Category, Media Type, Size, Description and the vendor costs you know. Leave unknown terms blank.
B13: Pricing conventions | C13: Vendor Cost columns are TOTALS for that term (3 Months = total for a 3-month flight). Where a base only sells a longer term, the 1 Month column is blank and Min Term shows the shortest term sold. Marquees and other per-unit items are priced per unit unless the description says otherwise.
B14: Client price rule | C14: Client Price = Vendor Cost / (1 - margin), rounded to the nearest $25 (Settings tab). Standard military margin is 50% (vendor x 2). Competitive bids may use a lower margin - change it in the proposal builder, not here.
B15: Production | C15: Production is never included in the media price. Standard production (quantity of 1): Poster 22x28 $100, Banner 3x6 $350. Other sizes: inquire. Where a base quoted its own production, it is in the Vendor Production Cost column.
B16: Review Flag | C16: "No price on file" = the base lists the item but we have no cost (inquire). "Rate card older than 2025" = reconfirm with the base before quoting. "Source formula errors" = the old master had #VALUE! in that row; verify against the base rate card in Box > Military > 2 Military Installations.
B17: Box source | C17: Every row carries the Box folder of the installation and the newest rate-card file in it ("Open in Box"). When you take a price from a new file, paste its Box link in the app (Update pricing) or in these columns.
B18: Proposal builder | C18: The web app (military/index.html in the EMC_AI_Tool repo) reads this file: use "Load rate card" in the app to pull in your latest edits, then build the proposal and export the client and internal Excel files.

Sheet Settings
A1: Setting | B1: Value | C1: Notes
A2: Standard margin (share of client price kept by Wilkins) | B2: 0.5 | C2: Client price = Vendor cost / (1 - margin). 50% = vendor x 2, the standard military markup. Competitive bids have used 30%.
A3: Round client prices to nearest | B3: 25 | C3: Matches the rounding used in the prior master list ($25).
A4: Standard production - Poster 22"W x 28"H (client price) | B4: 100 | C4: Per David, Sep 22 2026 (raised because frames must ship separately).
A5: Standard production - Banner 3'H x 6'W (client price) | B5: 350 | C5: Per David, Sep 22 2026.
A6: Est. printer cost - Poster | B6: 50 | C6: Estimate; update from the printer quote.
A7: Est. printer cost - Banner 3x6 | B7: 96 | C7: Printer quote (Cecily): $95.51 with ground shipping.
A8: Default campaign length (months) | B8: 3 | C8: A one-month campaign is not as effective; pricing is quoted on a three-month campaign.
A9: Standard pricing method | B9: Monthly rate x months | C9: House rule: use the 1-month rate x months (not the discounted term price) unless it is a competitive bid.
A10: Rate card year considered current | B10: 2025 | C10: Cards from 2025/2026 are good; older cards should be reconfirmed with the base.

Sheet Rate Card
A1: ID | B1: Base | C1: Also known as | D1: State | E1: DMA / Metro | F1: Zip | G1: Branch | H1: Category | I1: Media Type | J1: Ad Unit Size | K1: Description | L1: Min Term (mo) | M1: Vendor Cost 1 Month | N1: Vendor Cost 3 Months | O1: Vendor Cost 6 Months | P1: Vendor Cost 12 Months | Q1: Vendor Production Cost | R1: Client Price 1 Month | S1: Client Price 3 Months | T1: Client Price 6 Months | U1: Client Price 12 Months | V1: Client Production Price | W1: Active Duty (ref.) | X1: Dependents (ref.) | Y1: Rate Card Year | Z1: Last Updated | AA1: Notes | AB1: Review Flag | AC1: Source | AD1: Rate card file in Box | AE1: Link to rate card file | AF1: Box folder
A2: AK-EIELSONA-001 | B2: Eielson AFB | D2: AK | E2: Fairbanks | F2: 99702 | G2: Air Force | H2: Digital | I2: Digital Monitor Network | J2: 1920pxW x 1080pxH | K2: Your static ad will appear on the indoor digital monitors in on-base facilities. | L2: 1 | M2: 200 | N2: 600 | O2: 1100 | P2: 2100 | Q2: 0 | R2: =IF(ISNUMBER(M2),ROUND(M2/(1-Settings!$B$2)/Settings!$B$3,0)*Settings!$B$3,"") | S2: =IF(ISNUMBER(N2),ROUND(N2/(1-Settings!$B$2)/Settings!$B$3,0)*Settings!$B$3,"") | T2: =IF(ISNUMBER(O2),ROUND(O2/(1-Settings!$B$2)/Settings!$B$3,0)*Settings!$B$3,"") | U2: =IF(ISNUMBER(P2),ROUND(P2/(1-Settings!$B$2)/Settings!$B$3,0)*Settings!$B$3,"") | V2: =IF(ISNUMBER(Q2),ROUND(Q2/(1-Settings!$B$2)/Settings!$B$3,0)*Settings!$B$3,"") | W2: 1958 | X2: 2424 | AA2: Inventory master 6/2026 lists Digital Marquee at $3,000 (1 mo) | AC2: MasterMilitaryOnBaseList 12.2.25 NS.xlsx | AD2: Eielson AFB_Advertising Rates_2026.pptx | AE2: Open in Box | AF2: Open in Box
A3: AK-EIELSONA-002 | B3: Eielson AFB | D3: AK | E3: Fairbanks | F3: 99702 | G3: Air Force | H3: Digital | I3: Outdoor Marquee | J3: TBD | K3: Your ad will appear on one outdoor marquee. | L3: 1 | M3: 1000 | N3: 3000 | O3: 5500 | P3: 10500 | Q3: 0 | R3: =IF(ISNUMBER(M3),ROUND(M3/(1-Settings!$B$2)/Settings!$B$3,0)*Settings!$B$3,"") | S3: =IF(ISNUMBER(N3),ROUND(N3/(1-Settings!$B$2)/Settings!$B$3,0)*Settings!$B$3,"") | T3: =IF(ISNUMBER(O3),ROUND(O3/(1-Settings!$B$2)/Settings!$B$3,0)*Settings!$B$3,"") | U3: =IF(ISNUMBER(P3),ROUND(P3/(1-Settings!$B$2)/Settings!$B$3,0)*Settings!$B$3,"") | V3: =IF(ISNUMBER(Q3),ROUND(Q3/(1-Settings!$B$2)/Settings!$B$3,0)*Settings!$B$3,"") | W3: 1958 | X3: 2424 | AA3: Inventory master 6/2026 lists Digital Marquee at $3,000 (1 mo) | AC3: MasterMilitaryOnBaseList 12.2.25 NS.xlsx | AD3: Eielson AFB_Advertising Rates_2026.pptx | AE3: Open in Box | AF3: Open in Box
A4: AK-EIELSONA-005 | B4: Eielson AFB | D4: AK | E4: Fairbanks | F4: 99702 | G4: Air Force | H4: Print & Publications | I4: Brochure/Flyer Placement | J4: TBD | K4: Your brochure or flyer will be distributed in an approved installation facility. | L4: 1 | M4: 50 | N4: 150 | O4: 275 | P4: 525 | Q4: 0 | R4: =IF(ISNUMBER(M4),ROUND(M4/(1-Settings!$B$2)/Settings!$B$3,0)*Settings!$B$3,"") | S4: =IF(ISNUMBER(N4),ROUND(N4/(1-Settings!$B$2)/Settings!$B$3,0)*Settings!$B$3,"") | T4: =IF(ISNUMBER(O4),ROUND(O4/(1-Settings!$B$2)/Settings!$B$3,0)*Settings!$B$3,"") | U4: =IF(ISNUMBER(P4),ROUND(P4/(1-Settings!$B$2)/Settings!$B$3,0)*Settings!$B$3,"") | V4: =IF(ISNUMBER(Q4),ROUND(Q4/(1-Settings!$B$2)/Settings!$B$3,0)*Settings!$B$3,"") | W4: 1958 | X4: 2424 | AC4: MasterMilitaryOnBaseList 12.2.25 NS.xlsx | AD4: Eielson AFB_Advertising Rates_2026.pptx | AE4: Open in Box | AF4: Open in Box
A5: AK-EIELSONA-006 | B5: Eielson AFB | D5: AK | E5: Fairbanks | F5: 99702 | G5: Air Force | H5: Sponsorship & Other | I5: Newcomers Info Fair | J5: TBD | K5: Newcomers Info Fair is held once a month in the Yukon Ballroom | L5: 1 | M5: 50 | N5: 150 | O5: 300 | P5: 600 | Q5: 0 | R5: =IF(ISNUMBER(M5),ROUND(M5/(1-Settings!$B$2)/Settings!$B$3,0)*Settings!$B$3,"") | S5: =IF(ISNUMBER(N5),ROUND(N5/(1-Settings!$B$2)/Settings!$B$3,0)*Settings!$B$3,"") | T5: =IF(ISNUMBER(O5),ROUND(O5/(1-Settings!$B$2)/Settings!$B$3,0)*Settings!$B$3,"") | U5: =IF(ISNUMBER(P5),ROUND(P5/(1-Settings!$B$2)/Settings!$B$3,0)*Settings!$B$3,"") | V5: =IF(ISNUMBER(Q5),ROUND(Q5/(1-Settings!$B$2)/Settings!$B$3,0)*Settings!$B$3,"") | W5: 1958 | X5: 2424 | AC5: MasterMilitaryOnBaseList 12.2.25 NS.xlsx | AD5: Eielson AFB_Advertising Rates_2026.pptx | AE5: Open in Box | AF5: Open in Box
A6: AK-EIELSONA-003 | B6: Eielson AFB | D6: AK | E6: Fairbanks | F6: 99702 | G6: Air Force | H6: Standard Media | I6: Banners | J6: TBD | K6: Your Banner will be hung in an approved on base facilities | L6: 1 | M6: 1000 | N6: 3000 | O6: 5500 | P6: 10500 | Q6: 200 | R6: =IF(ISNUMBER(M6),ROUND(M6/(1-Settings!$B$2)/Settings!$B$3,0)*Settings!$B$3,"") | S6: =IF(ISNUMBER(N6),ROUND(N6/(1-Settings!$B$2)/Settings!$B$3,0)*Settings!$B$3,"") | T6: =IF(ISNUMBER(O6),ROUND(O6/(1-Settings!$B$2)/Settings!$B$3,0)*Settings!$B$3,"") | U6: =IF(ISNUMBER(P6),ROUND(P6/(1-Settings!$B$2)/Settings!$B$3,0)*Settings!$B$3,"") | V6: =IF(ISNUMBER(Q6),ROUND(Q6/(1-Settings!$B$2)/Settings!$B$3,0)*Settings!$B$3,"") | W6: 1958 | X6: 2424 | AC6: MasterMilitaryOnBaseList 12.2.25 NS.xlsx | AD6: Eielson AFB_Advertising Rates_2026.pptx | AE6: Open in Box | AF6: Open in Box
A7: AK-EIELSONA-004 | B7: Eielson AFB | D7: AK | E7: Fairbanks | F7: 99702 | G7: Air Force | H7: Standard Media | I7: Product Display | K7: Your product will be displayed at an approved installation facility. | L7: 1 | M7: 1000 | N7: 3000 | O7: 5500 | P7: 10500 | Q7: 0 | R7: =IF(ISNUMBER(M7),ROUND(M7/(1-Settings!$B$2)/Settings!$B$3,0)*Settings!$B$3,"") | S7: =IF(ISNUMBER(N7),ROUND(N7/(1-Settings!$B$2)/Settings!$B$3,0)*Settings!$B$3,"") | T7: =IF(ISNUMBER(O7),ROUND(O7/(1-Settings!$B$2)/Settings!$B$3,0)*Settings!$B$3,"") | U7: =IF(ISNUMBER(P7),ROUND(P7/(1-Settings!$B$2)/Settings!$B$3,0)*Settings!$B$3,"") | V7: =IF(ISNUMBER(Q7),ROUND(Q7/(1-Settings!$B$2)/Settings!$B$3,0)*Settings!$B$3,"") | W7: 1958 | X7: 2424 | AC7: MasterMilitaryOnBaseList 12.2.25 NS.xlsx | AD7: Eielson AFB_Advertising Rates_2026.pptx | AE7: Open in Box | AF7: Open in Box
A8: AK-EIELSONA-008 | B8: Eielson AFB | D8: AK | E8: Fairbanks | G8: Air Force | H8: Web & Email | I8: Web Ad | K8: Your ad will appear on the installation MWR / FSS website. | L8: 1 | M8: 1000 | R8: =IF(ISNUMBER(M8),ROUND(M8/(1-Settings!$B$2)/Settings!$B$3,0)*Settings!$B$3,"") | S8: =IF(ISNUMBER(N8),ROUND(N8/(1-Settings!$B$2)/Settings!$B$3,0)*Settings!$B$3,"") | T8: =IF(ISNUMBER(O8),ROUND(O8/(1-Settings!$B$2)/Settings!$B$3,0)*Settings!$B$3,"") | U8: =IF(ISNUMBER(P8),ROUND(P8/(1-Settings!$B$2)/Settings!$B$3,0)*Settings!$B$3,"") | V8: =IF(ISNUMBER(Q8),ROUND(Q8/(1-Settings!$B$2)/Settings!$B$3,0)*Settings!$B$3,"") | W8: 1958 | X8: 2424 | Y8: 2026 | Z8: 2026-06 | AC8: Military - National Publication Inventory Master_June 2026.xlsx | AD8: Eielson AFB_Advertising Rates_2026.pptx | AE8: Open in Box | AF8: Open in Box
A9: AK-EIELSONA-007 | B9: Eielson AFB | D9: AK | E9: Fairbanks | G9: Air Force | H9: Web & Email | I9: Weekly E-Newsletter Ad | K9: Your ad will appear in the weekly e-newsletter emailed to the installation community. | L9: 1 | M9: 50 | R9: =IF(ISNUMBER(M9),ROUND(M9/(1-Settings!$B$2)/Settings!$B$3,0)*Settings!$B$3,"") | S9: =IF(ISNUMBER(N9),ROUND(N9/(1-Settings!$B$2)/Settings!$B$3,0)*Settings!$B$3,"") | T9: =IF(ISNUMBER(O9),ROUND(O9/(1-Settings!$B$2)/Settings!$B$3,0)*Settings!$B$3,"") | U9: =IF(ISNUMBER(P9),ROUND(P9/(1-Settings!$B$2)/Settings!$B$3,0)*Settings!$B$3,"") | V9: =IF(ISNUMBER(Q9),ROUND(Q9/(1-Settings!$B$2)/Settings!$B$3,0)*Settings!$B$3,"") | W9: 1958 | X9: 2424 | Y9: 2026 | Z9: 2026-06 | AC9: Military - National Publication Inventory Master_June 2026.xlsx | AD9: Eielson AFB_Advertising Rates_2026.pptx | AE9: Open in Box | AF9: Open in Box
A10: AK-FORTGREE-001 | B10: Fort Greely | D10: AK | E10: Fairbanks, AK | G10: Army | H10: Digital | I10: Digital Marquee | J10: 3 screens | K10: Your ad will appear on the 3-screen digital marquee(s) on the installation. | L10: 1 | M10: 75 | R10: =IF(ISNUMBER(M10),ROUND(M10/(1-Settings!$B$2)/Settings!$B$3,0)*Settings!$B$3,"") | S10: =IF(ISNUMBER(N10),ROUND(N10/(1-Settings!$B$2)/Settings!$B$3,0)*Settings!$B$3,"") | T10: =IF(ISNUMBER(O10),ROUND(O10/(1-Settings!$B$2)/Settings!$B$3,0)*Settings!$B$3,"") | U10: =IF(ISNUMBER(P10),ROUND(P10/(1-Settings!$B$2)/Settings!$B$3,0)*Settings!$B$3,"") | V10: =IF(ISNUMBER(Q10),ROUND(Q10/(1-Settings!$B$2)/Settings!$B$3,0)*Settings!$B$3,"") | Y10: 2026 | Z10: 2026-06 | AC10: Military - National Digital Inventory Master 6.3.26.xlsx | AD10: USAG Alaska Advertising Flyer_2026.png | AE10: Open in Box | AF10: Open in Box
A11: AK-FORTGREE-002 | B11: Fort Greely | D11: AK | E11: Fairbanks, AK | G11: Army | H11: Web & Email | I11: Web Ad | K11: Your ad will appear on the installation MWR / FSS website. | L11: 3 | N11: 50 | R11: =IF(ISNUMBER(M11),ROUND(M11/(1-Settings!$B$2)/Settings!$B$3,0)*Settings!$B$3,"") | S11: =IF(ISNUMBER(N11),ROUND(N11/(1-Settings!$B$2)/Settings!$B$3,0)*Settings!$B$3,"") | T11: =IF(ISNUMBER(O11),ROUND(O11/(1-Settings!$B$2)/Settings!$B$3,0)*Settings!$B$3,"") | U11: =IF(ISNUMBER(P11),ROUND(P11/(1-Settings!$B$2)/Settings!$B$3,0)*Settings!$B$3,"") | V11: =IF(ISNUMBER(Q11),ROUND(Q11/(1-Settings!$B$2)/Settings!$B$3,0)*Settings!$B$3,"") | W11: 407 | Y11: 2026 | Z11: 2026-06 | AA11: Sold quarterly | AC11: Military - National Publication Inventory Master_June 2026.xlsx | AD11: USAG Alaska Advertising Flyer_2026.png | AE11: Open in Box | AF11: Open in Box
A12: AK-FORTJONA-001 | B12: Fort Jonathan Wainwright | D12: AK | E12: Fairbanks, AK | G12: Army | H12: Digital | I12: Digital Marquee | J12: 7 screens | K12: Your ad will appear on the 7-screen digital marquee(s) on the installation. | L12: 1 | M12: 700 | R12: =IF(ISNUMBER(M12),ROUND(M12/(1-Settings!$B$2)/Settings!$B$3,0)*Settings!$B$3,"") | S12: =IF(ISNUMBER(N12),ROUND(N12/(1-Settings!$B$2)/Settings!$B$3,0)*Settings!$B$3,"") | T12: =IF(ISNUMBER(O12),ROUND(O12/(1-Settings!$B$2)/Settings!$B$3,0)*Settings!$B$3,"") | U12: =IF(ISNUMBER(P12),ROUND(P12/(1-Settings!$B$2)/Settings!$B$3,0)*Settings!$B$3,"") | V12: =IF(ISNUMBER(Q12),ROUND(Q12/(1-Settings!$B$2)/Settings!$B$3,0)*Settings!$B$3,"") | W12: 6117 | X12: 6995 | Y12: 2026 | Z12: 2026-06 | AC12: Military - National Digital Inventory Master 6.3.26.xlsx | AD12: USAG Alaska Advertising Flyer_2026.png | AE12: Open in Box | AF12: Open in Box
A13: AK-FORTJONA-002 | B13: Fort Jonathan Wainwright | D13: AK | E13: Fairbanks, AK | G13: Army | H13: Web & Email | I13: Web Ad | K13: Your ad will appear on the installation MWR / FSS website. | L13: 3 | N13: 300 | R13: =IF(ISNUMBER(M13),ROUND(M13/(1-Settings!$B$2)/Settings!$B$3,0)*Settings!$B$3,"") | S13: =IF(ISNUMBER(N13),ROUND(N13/(1-Settings!$B$2)/Settings!$B$3,0)*Settings!$B$3,"") | T13: =IF(ISNUMBER(O13),ROUND(O13/(1-Settings!$B$2)/Settings!$B$3,0)*Settings!$B$3,"") | U13: =IF(ISNUMBER(P13),ROUND(P13/(1-Settings!$B$2)/Settings!$B$3,0)*Settings!$B$3,"") | V13: =IF(ISNUMBER(Q13),ROUND(Q13/(1-Settings!$B$2)/Settings!$B$3,0)*Settings!$B$3,"") | W13: 6117 | X13: 6995 | Y13: 2026 | Z13: 2026-06 | AA13: Sold quarterly | AC13: Military - National Publication Inventory Master_June 2026.xlsx | AD13: USAG Alaska Advertising Flyer_2026.png | AE13: Open in Box | AF13: Open in Box
A14: AK-JBERELME-001 | B14: JBER - Elmendorf AFB | C14: Joint Base Elmendorf-Richardson | D14: AK | E14: Anchorage | F14: 99506 | G14: Air Force | H14: Digital | I14: Bowling Score Monitors | K14: Your ad will be shown on the monitors in the largest bowling center in the Air Force | L14: 3 | N14: 750 | O14: 1500 | P14: 3000 | Q14: 0 | R14: =IF(ISNUMBER(M14),ROUND(M14/(1-Settings!$B$2)/Settings!$B$3,0)*Settings!$B$3,"") | S14: =IF(ISNUMBER(N14),ROUND(N14/(1-Settings!$B$2)/Settings!$B$3,0)*Settings!$B$3,"") | T14: =IF(ISNUMBER(O14),ROUND(O14/(1-Settings!$B$2)/Settings!$B$3,0)*Settings!$B$3,"") | U14: =IF(ISNUMBER(P14),ROUND(P14/(1-Settings!$B$2)/Settings!$B$3,0)*Settings!$B$3,"") | V14: =IF(ISNUMBER(Q14),ROUND(Q14/(1-Settings!$B$2)/Settings!$B$3,0)*Settings!$B$3,"") | W14: 5504 | X14: 7035 | AA14: Inventory master 6/2026 lists Golf Scorecard Ad at $500 (3 mo) | AC14: MasterMilitaryOnBaseList 12.2.25 NS.xlsx | AD14: Sponsorship & Advertising Rate Sheet_2026.pdf | AE14: Open in Box | AF14: Open in Box
A15: AK-JBERELME-002 | B15: JBER - Elmendorf AFB | C15: Joint Base Elmendorf-Richardson | D15: AK | E15: Anchorage | F15: 99506 | G15: Air Force | H15: Digital | I15: Bowling Table Tents | K15: Your ad will be on table tents placed on the tables in the largest bowling center in the Air Force | L15: 3 | N15: 600 | O15: 1200 | P15: 1000 | Q15: 0 | R15: =IF(ISNUMBER(M15),ROUND(M15/(1-Settings!$B$2)/Settings!$B$3,0)*Settings!$B$3,"") | S15: =IF(ISNUMBER(N15),ROUND(N15/(1-Settings!$B$2)/Settings!$B$3,0)*Settings!$B$3,"") | T15: =IF(ISNUMBER(O15),ROUND(O15/(1-Settings!$B$2)/Settings!$B$3,0)*Settings!$B$3,"") | U15: =IF(ISNUMBER(P15),ROUND(P15/(1-Settings!$B$2)/Settings!$B$3,0)*Settings!$B$3,"") | V15: =IF(ISNUMBER(Q15),ROUND(Q15/(1-Settings!$B$2)/Settings!$B$3,0)*Settings!$B$3,"") | W15: 5504 | X15: 7035 | AC15: MasterMilitaryOnBaseList 12.2.25 NS.xlsx | AD15: Sponsorship & Advertising Rate Sheet_2026.pdf | AE15: Open in Box | AF15: Open in Box
A16: AK-JBERELME-003 | B16: JBER - Elmendorf AFB | C16: Joint Base Elmendorf-Richardson | D16: AK | E16: Anchorage | F16: 99506 | G16: Air Force | H16: Digital | I16: Digital Monitor Network | K16: Your ad will appear on 36 digital monitors. | L16: 3 | N16: 800 | O16: 1600 | P16: 3200 | Q16: 0 | R16: =IF(ISNUMBER(M16),ROUND(M16/(1-Settings!$B$2)/Settings!$B$3,0)*Settings!$B$3,"") | S16: =IF(ISNUMBER(N16),ROUND(N16/(1-Settings!$B$2)/Settings!$B$3,0)*Settings!$B$3,"") | T16: =IF(ISNUMBER(O16),ROUND(O16/(1-Settings!$B$2)/Settings!$B$3,0)*Settings!$B$3,"") | U16: =IF(ISNUMBER(P16),ROUND(P16/(1-Settings!$B$2)/Settings!$B$3,0)*Settings!$B$3,"") | V16: =IF(ISNUMBER(Q16),ROUND(Q16/(1-Settings!$B$2)/Settings!$B$3,0)*Settings!$B$3,"") | W16: 5504 | X16: 7035 | AC16: MasterMilitaryOnBaseList 12.2.25 NS.xlsx | AD16: Sponsorship & Advertising Rate Sheet_2026.pdf | AE16: Open in Box | AF16: Open in Box
A17: AK-JBERELME-004 | B17: JBER - Elmendorf AFB | C17: Joint Base Elmendorf-Richardson | D17: AK | E17: Anchorage | F17: 99506 | G17: Air Force | H17: Digital | I17: Lane Sweepers | K17: Your ad will cover 40 lanes | L17: 12 | P17: 5000 | Q17: 0 | R17: =IF(ISNUMBER(M17),ROUND(M17/(1-Settings!$B$2)/Settings!$B$3,0)*Settings!$B$3,"") | S17: =IF(ISNUMBER(N17),ROUND(N17/(1-Settings!$B$2)/Settings!$B$3,0)*Settings!$B$3,"") | T17: =IF(ISNUMBER(O17),ROUND(O17/(1-Settings!$B$2)/Settings!$B$3,0)*Settings!$B$3,"") | U17: =IF(ISNUMBER(P17),ROUND(P17/(1-Settings!$B$2)/Settings!$B$3,0)*Settings!$B$3,"") | V17: =IF(ISNUMBER(Q17),ROUND(Q17/(1-Settings!$B$2)/Settings!$B$3,0)*Settings!$B$3,"") | W17: 5504 | X17: 7035 | AC17: MasterMilitaryOnBaseList 12.2.25 NS.xlsx | AD17: Sponsorship & Advertising Rate Sheet_2026.pdf | AE17: Open in Box | AF17: Open in Box
A18: AK-JBERELME-009 | B18: JBER - Elmendorf AFB | C18: Joint Base Elmendorf-Richardson | D18: AK | E18: Anchorage | F18: 99506 | G18: Air Force | H18: Large Format | I18: Snow Fencing | K18: Your ad will appear on a snow fence from November - May at Hillberg Ski Area | L18: 12 | P18: 10000 | Q18: 0 | R18: =IF(ISNUMBER(M18),ROUND(M18/(1-Settings!$B$2)/Settings!$B$3,0)*Settings!$B$3,"") | S18: =IF(ISNUMBER(N18),ROUND(N18/(1-Settings!$B$2)/Settings!$B$3,0)*Settings!$B$3,"") | T18: =IF(ISNUMBER(O18),ROUND(O18/(1-Settings!$B$2)/Settings!$B$3,0)*Settings!$B$3,"") | U18: =IF(ISNUMBER(P18),ROUND(P18/(1-Settings!$B$2)/Settings!$B$3,0)*Settings!$B$3,"") | V18: =IF(ISNUMBER(Q18),ROUND(Q18/(1-Settings!$B$2)/Settings!$B$3,0)*Settings!$B$3,"") | W18: 5504 | X18: 7035 | AC18: MasterMilitaryOnBaseList 12.2.25 NS.xlsx | AD18: Sponsorship & Advertising Rate Sheet_2026.pdf | AE18: Open in Box | AF18: Open in Box
A19: AK-JBERELME-010 | B19: JBER - Elmendorf AFB | C19: Joint Base Elmendorf-Richardson | D19: AK | E19: Anchorage | F19: 99506 | G19: Air Force | H19: Print & Publications | I19: Cabin Book Ads | K19: Your ad will appear in the cabin book ads seasonally (May - September) | L19: 3 | N19: 500 | Q19: 0 | R19: =IF(ISNUMBER(M19),ROUND(M19/(1-Settings!$B$2)/Settings!$B$3,0)*Settings!$B$3,"") | S19: =IF(ISNUMBER(N19),ROUND(N19/(1-Settings!$B$2)/Settings!$B$3,0)*Settings!$B$3,"") | T19: =IF(ISNUMBER(O19),ROUND(O19/(1-Settings!$B$2)/Settings!$B$3,0)*Settings!$B$3,"") | U19: =IF(ISNUMBER(P19),ROUND(P19/(1-Settings!$B$2)/Settings!$B$3,0)*Settings!$B$3,"") | V19: =IF(ISNUMBER(Q19),ROUND(Q19/(1-Settings!$B$2)/Settings!$B$3,0)*Settings!$B$3,"") | W19: 5504 | X19: 7035 | AC19: MasterMilitaryOnBaseList 12.2.25 NS.xlsx | AD19: Sponsorship & Advertising Rate Sheet_2026.pdf | AE19: Open in Box | AF19: Open in Box
A20: AK-JBERELME-011 | B20: JBER - Elmendorf AFB | C20: Joint Base Elmendorf-Richardson | D20: AK | E20: Anchorage | F20: 99506 | G20: Air Force | H20: Print & Publications | I20: Golf Score Cards | K20: Your ads will appear on the score cards from May - September at the Moose Run Golf Course | L20: 12 | P20: 500 | Q20: 0 | R20: =IF(ISNUMBER(M20),ROUND(M20/(1-Settings!$B$2)/Settings!$B$3,0)*Settings!$B$3,"") | S20: =IF(ISNUMBER(N20),ROUND(N20/(1-Settings!$B$2)/Settings!$B$3,0)*Settings!$B$3,"") | T20: =IF(ISNUMBER(O20),ROUND(O20/(1-Settings!$B$2)/Settings!$B$3,0)*Settings!$B$3,"") | U20: =IF(ISNUMBER(P20),ROUND(P20/(1-Settings!$B$2)/Settings!$B$3,0)*Settings!$B$3,"") | V20: =IF(ISNUMBER(Q20),ROUND(Q20/(1-Settings!$B$2)/Settings!$B$3,0)*Settings!$B$3,"") | W20: 5504 | X20: 7035 | AA20: Inventory master 6/2026 lists Golf Scorecard Ad at $500 (3 mo) | AC20: MasterMilitaryOnBaseList 12.2.25 NS.xlsx | AD20: Sponsorship & Advertising Rate Sheet_2026.pdf | AE20: Open in Box | AF20: Open in Box
A21: AK-JBERELME-012 | B21: JBER - Elmendorf AFB | C21: Joint Base Elmendorf-Richardson | D21: AK | E21: Anchorage | F21: 99506 | G21: Air Force | H21: Print & Publications | I21: Magazine Ad | J21: Full Page | K21: Your ad will appear in the JBER Life! Magazine (a 40 page magazine with 5,000 copies distributed across the installation and published online) | L21: 1 | M21: 500 | N21: 1500 | O21: 3000 | P21: 6000 | Q21: 0 | R21: =IF(ISNUMBER(M21),ROUND(M21/(1-Settings!$B$2)/Settings!$B$3,0)*Settings!$B$3,"") | S21: =IF(ISNUMBER(N21),ROUND(N21/(1-Settings!$B$2)/Settings!$B$3,0)*Settings!$B$3,"") | T21: =IF(ISNUMBER(O21),ROUND(O21/(1-Settings!$B$2)/Settings!$B$3,0)*Settings!$B$3,"") | U21: =IF(ISNUMBER(P21),ROUND(P21/(1-Settings!$B$2)/Settings!$B$3,0)*Settings!$B$3,"") | V21: =IF(ISNUMBER(Q21),ROUND(Q21/(1-Settings!$B$2)/Settings!$B$3,0)*Settings!$B$3,"") | W21: 5504 | X21: 7035 | AA21: Inventory master 6/2026 lists Magazine Ad at $800 (3 mo) | AC21: MasterMilitaryOnBaseList 12.2.25 NS.xlsx | AD21: Sponsorship & Advertising Rate Sheet_2026.pdf | AE21: Open in Box | AF21: Open in Box
A22: AK-JBERELME-013 | B22: JBER - Elmendorf AFB | C22: Joint Base Elmendorf-Richardson | D22: AK | E22: Anchorage | F22: 99506 | G22: Air Force | H22: Print & Publications | I22: Summer Outdoor Adventure Guide | K22: 10,000 copies combined circulated installation wide and published online. Produced once for summer and once for winter. | L22: 12 | P22: 900 | Q22: 0 | R22: =IF(ISNUMBER(M22),ROUND(M22/(1-Settings!$B$2)/Settings!$B$3,0)*Settings!$B$3,"") | S22: =IF(ISNUMBER(N22),ROUND(N22/(1-Settings!$B$2)/Settings!$B$3,0)*Settings!$B$3,"") | T22: =IF(ISNUMBER(O22),ROUND(O22/(1-Settings!$B$2)/Settings!$B$3,0)*Settings!$B$3,"") | U22: =IF(ISNUMBER(P22),ROUND(P22/(1-Settings!$B$2)/Settings!$B$3,0)*Settings!$B$3,"") | V22: =IF(ISNUMBER(Q22),ROUND(Q22/(1-Settings!$B$2)/Settings!$B$3,0)*Settings!$B$3,"") | W22: 5504 | X22: 7035 | AA22: Inventory master 6/2026 lists Guide / Map Ad at $900 (3 mo) | AC22: MasterMilitaryOnBaseList 12.2.25 NS.xlsx | AD22: Sponsorship & Advertising Rate Sheet_2026.pdf | AE22: Open in Box | AF22: Open in Box
A23: AK-JBERELME-014 | B23: JBER - Elmendorf AFB | C23: Joint Base Elmendorf-Richardson | D23: AK | E23: Anchorage | F23: 99506 | G23: Air Force | H23: Print & Publications | I23: Winter Outdoor Adventure Guide | K23: 10,000 copies combined circulated installation wide and published online. $100 discount when you advertise in both books. Deadline: September 15 | L23: 12 | P23: 700 | Q23: 0 | R23: =IF(ISNUMBER(M23),ROUND(M23/(1-Settings!$B$2)/Settings!$B$3,0)*Settings!$B$3,"") | S23: =IF(ISNUMBER(N23),ROUND(N23/(1-Settings!$B$2)/Settings!$B$3,0)*Settings!$B$3,"") | T23: =IF(ISNUMBER(O23),ROUND(O23/(1-Settings!$B$2)/Settings!$B$3,0)*Settings!$B$3,"") | U23: =IF(ISNUMBER(P23),ROUND(P23/(1-Settings!$B$2)/Settings!$B$3,0)*Settings!$B$3,"") | V23: =IF(ISNUMBER(Q23),ROUND(Q23/(1-Settings!$B$2)/Settings!$B$3,0)*Settings!$B$3,"") | W23: 5504 | X23: 7035 | AA23: Inventory master 6/2026 lists Guide / Map Ad at $900 (3 mo) | AC23: MasterMilitaryOnBaseList 12.2.25 NS.xlsx | AD23: Sponsorship & Advertising Rate Sheet_2026.pdf | AE23: Open in Box | AF23: Open in Box
A24: AK-JBERELME-015 | B24: JBER - Elmendorf AFB | C24: Joint Base Elmendorf-Richardson | D24: AK | E24: Anchorage | F24: 99506 | G24: Air Force | H24: Sponsorship & Other | I24: Canopy - Golf Course | K24: Your ads will appear on a canopy from May - September at the Moose Run Golf Course | L24: 12 | P24: 1000 | Q24: 0 | R24: =IF(ISNUMBER(M24),ROUND(M24/(1-Settings!$B$2)/Settings!$B$3,0)*Settings!$B$3,"") | S24: =IF(ISNUMBER(N24),ROUND(N24/(1-Settings!$B$2)/Settings!$B$3,0)*Settings!$B$3,"") | T24: =IF(ISNUMBER(O24),ROUND(O24/(1-Settings!$B$2)/Settings!$B$3,0)*Settings!$B$3,"") | U24: =IF(ISNUMBER(P24),ROUND(P24/(1-Settings!$B$2)/Settings!$B$3,0)*Settings!$B$3,"") | V24: =IF(ISNUMBER(Q24),ROUND(Q24/(1-Settings!$B$2)/Settings!$B$3,0)*Settings!$B$3,"") | W24: 5504 | X24: 7035 | AC24: MasterMilitaryOnBaseList 12.2.25 NS.xlsx | AD24: Sponsorship & Advertising Rate Sheet_2026.pdf | AE24: Open in Box | AF24: Open in Box
A25: AK-JBERELME-016 | B25: JBER - Elmendorf AFB | C25: Joint Base Elmendorf-Richardson | D25: AK | E25: Anchorage | F25: 99506 | G25: Air Force | H25: Sponsorship & Other | I25: Chairlift - Ski Area | K25: Your ad will appear on a chairlift from November - March at the Hillberg Ski Area | L25: 12 | P25: 500 | Q25: 0 | R25: =IF(ISNUMBER(M25),ROUND(M25/(1-Settings!$B$2)/Settings!$B$3,0)*Settings!$B$3,"") | S25: =IF(ISNUMBER(N25),ROUND(N25/(1-Settings!$B$2)/Settings!$B$3,0)*Settings!$B$3,"") | T25: =IF(ISNUMBER(O25),ROUND(O25/(1-Settings!$B$2)/Settings!$B$3,0)*Settings!$B$3,"") | U25: =IF(ISNUMBER(P25),ROUND(P25/(1-Settings!$B$2)/Settings!$B$3,0)*Settings!$B$3,"") | V25: =IF(ISNUMBER(Q25),ROUND(Q25/(1-Settings!$B$2)/Settings!$B$3,0)*Settings!$B$3,"") | W25: 5504 | X25: 7035 | AC25: MasterMilitaryOnBaseList 12.2.25 NS.xlsx | AD25: Sponsorship & Advertising Rate Sheet_2026.pdf | AE25: Open in Box | AF25: Open in Box
A26: AK-JBERELME-017 | B26: JBER - Elmendorf AFB | C26: Joint Base Elmendorf-Richardson | D26: AK | E26: Anchorage | F26: 99506 | G26: Air Force | H26: Sponsorship & Other | I26: Driving Range Dividers | K26: Your ad will appear on a single the driving range dividers at the Moose Run Golf Course from May - September. | L26: 12 | P26: 350 | Q26: 0 | R26: =IF(ISNUMBER(M26),ROUND(M26/(1-Settings!$B$2)/Settings!$B$3,0)*Settings!$B$3,"") | S26: =IF(ISNUMBER(N26),ROUND(N26/(1-Settings!$B$2)/Settings!$B$3,0)*Settings!$B$3,"") | T26: =IF(ISNUMBER(O26),ROUND(O26/(1-Settings!$B$2)/Settings!$B$3,0)*Settings!$B$3,"") | U26: =IF(ISNUMBER(P26),ROUND(P26/(1-Settings!$B$2)/Settings!$B$3,0)*Settings!$B$3,"") | V26: =IF(ISNUMBER(Q26),ROUND(Q26/(1-Settings!$B$2)/Settings!$B$3,0)*Settings!$B$3,"") | W26: 5504 | X26: 7035 | AC26: MasterMilitaryOnBaseList 12.2.25 NS.xlsx | AD26: Sponsorship & Advertising Rate Sheet_2026.pdf | AE26: Open in Box | AF26: Open in Box
A27: AK-JBERELME-018 | B27: JBER - Elmendorf AFB | C27: Joint Base Elmendorf-Richardson | D27: AK | E27: Anchorage | F27: 99506 | G27: Air Force | H27: Sponsorship & Other | I27: Newcomers Info Bag | K27: Your ad will appear in the installation newcomers info bags. | L27: 3 | N27: 525 | O27: 1000 | P27: 2000 | Q27: 0 | R27: =IF(ISNUMBER(M27),ROUND(M27/(1-Settings!$B$2)/Settings!$B$3,0)*Settings!$B$3,"") | S27: =IF(ISNUMBER(N27),ROUND(N27/(1-Settings!$B$2)/Settings!$B$3,0)*Settings!$B$3,"") | T27: =IF(ISNUMBER(O27),ROUND(O27/(1-Settings!$B$2)/Settings!$B$3,0)*Settings!$B$3,"") | U27: =IF(ISNUMBER(P27),ROUND(P27/(1-Settings!$B$2)/Settings!$B$3,0)*Settings!$B$3,"") | V27: =IF(ISNUMBER(Q27),ROUND(Q27/(1-Settings!$B$2)/Settings!$B$3,0)*Settings!$B$3,"") | W27: 5504 | X27: 7035 | AC27: MasterMilitaryOnBaseList 12.2.25 NS.xlsx | AD27: Sponsorship & Advertising Rate Sheet_2026.pdf | AE27: Open in Box | AF27: Open in Box
A28: AK-JBERELME-005 | B28: JBER - Elmendorf AFB | C28: Joint Base Elmendorf-Richardson | D28: AK | E28: Anchorage | F28: 99506 | G28: Air Force | H28: Standard Media | I28: Banners | K28: Your ad will apper in an approved installation facility. | L28: 6 | O28: 1000 | P28: 2000 | Q28: 200 | R28: =IF(ISNUMBER(M28),ROUND(M28/(1-Settings!$B$2)/Settings!$B$3,0)*Settings!$B$3,"") | S28: =IF(ISNUMBER(N28),ROUND(N28/(1-Settings!$B$2)/Settings!$B$3,0)*Settings!$B$3,"") | T28: =IF(ISNUMBER(O28),ROUND(O28/(1-Settings!$B$2)/Settings!$B$3,0)*Settings!$B$3,"") | U28: =IF(ISNUMBER(P28),ROUND(P28/(1-Settings!$B$2)/Settings!$B$3,0)*Settings!$B$3,"") | V28: =IF(ISNUMBER(Q28),ROUND(Q28/(1-Settings!$B$2)/Settings!$B$3,0)*Settings!$B$3,"") | W28: 5504 | X28: 7035 | AC28: MasterMilitaryOnBaseList 12.2.25 NS.xlsx | AD28: Sponsorship & Advertising Rate Sheet_2026.pdf | AE28: Open in Box | AF28: Open in Box
A29: AK-JBERELME-006 | B29: JBER - Elmendorf AFB | C29: Joint Base Elmendorf-Richardson | D29: AK | E29: Anchorage | F29: 99506 | G29: Air Force | H29: Standard Media | I29: Golf Tee Signs | K29: Your ads will appear at one hole during golf season from May - September at the Moose Run Golf Course | L29: 12 | P29: 700 | Q29: 0 | R29: =IF(ISNUMBER(M29),ROUND(M29/(1-Settings!$B$2)/Settings!$B$3,0)*Settings!$B$3,"") | S29: =IF(ISNUMBER(N29),ROUND(N29/(1-Settings!$B$2)/Settings!$B$3,0)*Settings!$B$3,"") | T29: =IF(ISNUMBER(O29),ROUND(O29/(1-Settings!$B$2)/Settings!$B$3,0)*Settings!$B$3,"") | U29: =IF(ISNUMBER(P29),ROUND(P29/(1-Settings!$B$2)/Settings!$B$3,0)*Settings!$B$3,"") | V29: =IF(ISNUMBER(Q29),ROUND(Q29/(1-Settings!$B$2)/Settings!$B$3,0)*Settings!$B$3,"") | W29: 5504 | X29: 7035 | AC29: MasterMilitaryOnBaseList 12.2.25 NS.xlsx | AD29: Sponsorship & Advertising Rate Sheet_2026.pdf | AE29: Open in Box | AF29: Open in Box
A30: AK-JBERELME-007 | B30: JBER - Elmendorf AFB | C30: Joint Base Elmendorf-Richardson | D30: AK | E30: Anchorage | F30: 99506 | G30: Air Force | H30: Standard Media | I30: Posters | J30: 22"W x 28"H | K30: Your ad will appear at an approved installation facility. | L30: 3 | N30: 300 | O30: 600 | P30: 1200 | Q30: 100 | R30: =IF(ISNUMBER(M30),ROUND(M30/(1-Settings!$B$2)/Settings!$B$3,0)*Settings!$B$3,"") | S30: =IF(ISNUMBER(N30),ROUND(N30/(1-Settings!$B$2)/Settings!$B$3,0)*Settings!$B$3,"") | T30: =IF(ISNUMBER(O30),ROUND(O30/(1-Settings!$B$2)/Settings!$B$3,0)*Settings!$B$3,"") | U30: =IF(ISNUMBER(P30),ROUND(P30/(1-Settings!$B$2)/Settings!$B$3,0)*Settings!$B$3,"") | V30: =IF(ISNUMBER(Q30),ROUND(Q30/(1-Settings!$B$2)/Settings!$B$3,0)*Settings!$B$3,"") | W30: 5504 | X30: 7035 | AC30: MasterMilitaryOnBaseList 12.2.25 NS.xlsx | AD30: Sponsorship & Advertising Rate Sheet_2026.pdf | AE30: Open in Box | AF30: Open in Box
A31: AK-JBERELME-008 | B31: JBER - Elmendorf AFB | C31: Joint Base Elmendorf-Richardson | D31: AK | E31: Anchorage | F31: 99507 | G31: Air Force | H31: Standard Media | I31: Posters | J31: 24"W x 36"H | K31: Your ad will appear at an approved installation facility. | L31: 3 | N31: 400 | O31: 800 | P31: 1600 | Q31: 101 | R31: =IF(ISNUMBER(M31),ROUND(M31/(1-Settings!$B$2)/Settings!$B$3,0)*Settings!$B$3,"") | S31: =IF(ISNUMBER(N31),ROUND(N31/(1-Settings!$B$2)/Settings!$B$3,0)*Settings!$B$3,"") | T31: =IF(ISNUMBER(O31),ROUND(O31/(1-Settings!$B$2)/Settings!$B$3,0)*Settings!$B$3,"") | U31: =IF(ISNUMBER(P31),ROUND(P31/(1-Settings!$B$2)/Settings!$B$3,0)*Settings!$B$3,"") | V31: =IF(ISNUMBER(Q31),ROUND(Q31/(1-Settings!$B$2)/Settings!$B$3,0)*Settings!$B$3,"") | W31: 5504 | X31: 7035 | AC31: MasterMilitaryOnBaseList 12.2.25 NS.xlsx | AD31: Sponsorship & Advertising Rate Sheet_2026.pdf | AE31: Open in Box | AF31: Open in Box
A32: AK-JBERELME-019 | B32: JBER - Elmendorf AFB | D32: AK | E32: Anchorage | G32: Air Force | H32: Web & Email | I32: Web Ad | K32: Your ad will appear on the installation MWR / FSS website. | L32: 3 | N32: 800 | R32: =IF(ISNUMBER(M32),ROUND(M32/(1-Settings!$B$2)/Settings!$B$3,0)*Settings!$B$3,"") | S32: =IF(ISNUMBER(N32),ROUND(N32/(1-Settings!$B$2)/Settings!$B$3,0)*Settings!$B$3,"") | T32: =IF(ISNUMBER(O32),ROUND(O32/(1-Settings!$B$2)/Settings!$B$3,0)*Settings!$B$3,"") | U32: =IF(ISNUMBER(P32),ROUND(P32/(1-Settings!$B$2)/Settings!$B$3,0)*Settings!$B$3,"") | V32: =IF(ISNUMBER(Q32),ROUND(Q32/(1-Settings!$B$2)/Settings!$B$3,0)*Settings!$B$3,"") | W32: 5504 | X32: 7035 | Y32: 2026 | Z32: 2026-06 | AA32: Sold quarterly | AC32: Military - National Publication Inventory Master_June 2026.xlsx | AD32: Sponsorship & Advertising Rate Sheet_2026.pdf | AE32: Open in Box | AF32: Open in Box
A33: AL-FORTNOVO-001 | B33: Fort Novosel | C33: Fort Rucker | D33: AL | E33: Montgomery | F33: 36323 | G33: Army | H33: Digital | I33: Bowling Scoring Monitors | K33: Your ad will appear on all digital scoring monitors. | L33: 1 | M33: 200 | N33: 600 | O33: 1200 | P33: 2400 | Q33: 0 | R33: =IF(ISNUMBER(M33),ROUND(M33/(1-Settings!$B$2)/Settings!$B$3,0)*Settings!$B$3,"") | S33: =IF(ISNUMBER(N33),ROUND(N33/(1-Settings!$B$2)/Settings!$B$3,0)*Settings!$B$3,"") | T33: =IF(ISNUMBER(O33),ROUND(O33/(1-Settings!$B$2)/Settings!$B$3,0)*Settings!$B$3,"") | U33: =IF(ISNUMBER(P33),ROUND(P33/(1-Settings!$B$2)/Settings!$B$3,0)*Settings!$B$3,"") | V33: =IF(ISNUMBER(Q33),ROUND(Q33/(1-Settings!$B$2)/Settings!$B$3,0)*Settings!$B$3,"") | W33: 3860 | X33: 5945 | AC33: MasterMilitaryOnBaseList 12.2.25 NS.xlsx | AD33: Gate Marquees - Rucker_Specs.docx | AE33: Open in Box | AF33: Open in Box
A34: AL-FORTNOVO-002 | B34: Fort Novosel | C34: Fort Rucker | D34: AL | E34: Montgomery | F34: 36322 | G34: Army | H34: Digital | I34: Digital Monitor Network | K34: Your ad will appear on 11 digital monitors in approved installation facilities. | L34: 1 | M34: 250 | N34: 600 | O34: 1050 | P34: 1800 | Q34: 0 | R34: =IF(ISNUMBER(M34),ROUND(M34/(1-Settings!$B$2)/Settings!$B$3,0)*Settings!$B$3,"") | S34: =IF(ISNUMBER(N34),ROUND(N34/(1-Settings!$B$2)/Settings!$B$3,0)*Settings!$B$3,"") | T34: =IF(ISNUMBER(O34),ROUND(O34/(1-Settings!$B$2)/Settings!$B$3,0)*Settings!$B$3,"") | U34: =IF(ISNUMBER(P34),ROUND(P34/(1-Settings!$B$2)/Settings!$B$3,0)*Settings!$B$3,"") | V34: =IF(ISNUMBER(Q34),ROUND(Q34/(1-Settings!$B$2)/Settings!$B$3,0)*Settings!$B$3,"") | W34: 3860 | X34: 5945 | AC34: MasterMilitaryOnBaseList 12.2.25 NS.xlsx | AD34: Gate Marquees - Rucker_Specs.docx | AE34: Open in Box | AF34: Open in Box
A35: AL-FORTNOVO-003 | B35: Fort Novosel | C35: Fort Rucker | D35: AL | E35: Montgomery | F35: 36322 | G35: Army | H35: Digital | I35: Digital Signage (Gate Marquees) | K35: Your ad will appear on the digital gate marquees at the Ozark, Daleville, and Enterprise entrances reaching 26,000+ daily visitors. | L35: 1 | M35: 1000 | N35: 3000 | O35: 6000 | P35: 12000 | R35: =IF(ISNUMBER(M35),ROUND(M35/(1-Settings!$B$2)/Settings!$B$3,0)*Settings!$B$3,"") | S35: =IF(ISNUMBER(N35),ROUND(N35/(1-Settings!$B$2)/Settings!$B$3,0)*Settings!$B$3,"") | T35: =IF(ISNUMBER(O35),ROUND(O35/(1-Settings!$B$2)/Settings!$B$3,0)*Settings!$B$3,"") | U35: =IF(ISNUMBER(P35),ROUND(P35/(1-Settings!$B$2)/Settings!$B$3,0)*Settings!$B$3,"") | V35: =IF(ISNUMBER(Q35),ROUND(Q35/(1-Settings!$B$2)/Settings!$B$3,0)*Settings!$B$3,"") | W35: 3860 | X35: 5945 | AC35: MasterMilitaryOnBaseList 12.2.25 NS.xlsx | AD35: Gate Marquees - Rucker_Specs.docx | AE35: Open in Box | AF35: Open in Box
A36: AL-FORTNOVO-004 | B36: Fort Novosel | C36: Fort Rucker | D36: AL | E36: Montgomery | F36: 36322 | G36: Army | H36: Digital | I36: Digital Signage (Gate Marquees) | K36: Your ad will appear on the digital gate marquees at the Ozark, Daleville, and Enterprise entrances reaching 26,000+ daily visitors plus Silver Wings Golf Club marquee. | L36: 1 | M36: 1200 | N36: 3600 | O36: 7200 | P36: 14400 | R36: =IF(ISNUMBER(M36),ROUND(M36/(1-Settings!$B$2)/Settings!$B$3,0)*Settings!$B$3,"") | S36: =IF(ISNUMBER(N36),ROUND(N36/(1-Settings!$B$2)/Settings!$B$3,0)*Settings!$B$3,"") | T36: =IF(ISNUMBER(O36),ROUND(O36/(1-Settings!$B$2)/Settings!$B$3,0)*Settings!$B$3,"") | U36: =IF(ISNUMBER(P36),ROUND(P36/(1-Settings!$B$2)/Settings!$B$3,0)*Settings!$B$3,"") | V36: =IF(ISNUMBER(Q36),ROUND(Q36/(1-Settings!$B$2)/Settings!$B$3,0)*Settings!$B$3,"") | W36: 3860 | X36: 5945 | AC36: MasterMilitaryOnBaseList 12.2.25 NS.xlsx | AD36: Gate Marquees - Rucker_Specs.docx | AE36: Open in Box | AF36: Open in Box
A37: AL-FORTNOVO-005 | B37: Fort Novosel | C37: Fort Rucker | D37: AL | E37: Montgomery | F37: 36322 | G37: Army | H37: Digital | I37: Digital Signage (Gate Marquees) | K37: Your ad will appear on the Silver Wings Golf Club outdoor digital marquee | L37: 1 | M37: 400 | N37: 1200 | O37: 2400 | P37: 4800 | R37: =IF(ISNUMBER(M37),ROUND(M37/(1-Settings!$B$2)/Settings!$B$3,0)*Settings!$B$3,"") | S37: =IF(ISNUMBER(N37),ROUND(N37/(1-Settings!$B$2)/Settings!$B$3,0)*Settings!$B$3,"") | T37: =IF(ISNUMBER(O37),ROUND(O37/(1-Settings!$B$2)/Settings!$B$3,0)*Settings!$B$3,"") | U37: =IF(ISNUMBER(P37),ROUND(P37/(1-Settings!$B$2)/Settings!$B$3,0)*Settings!$B$3,"") | V37: =IF(ISNUMBER(Q37),ROUND(Q37/(1-Settings!$B$2)/Settings!$B$3,0)*Settings!$B$3,"") | W37: 3860 | X37: 5945 | AC37: MasterMilitaryOnBaseList 12.2.25 NS.xlsx | AD37: Gate Marquees - Rucker_Specs.docx | AE37: Open in Box | AF37: Open in Box
A38: AL-FORTNOVO-009 | B38: Fort Novosel | C38: Fort Rucker | D38: AL | E38: Montgomery | F38: 36322 | G38: Army | H38: Large Format | I38: Indoor Vinyl Banner and Counter Wraps | J38: Sizes Vary | K38: Your signs will be placed on the fencing that surrounds the ball fields, Lake Tholocco, the Lemon Lot, and The Flightline. | L38: 1 | M38: 1000 | N38: 3000 | O38: 6000 | P38: 12000 | R38: =IF(ISNUMBER(M38),ROUND(M38/(1-Settings!$B$2)/Settings!$B$3,0)*Settings!$B$3,"") | S38: =IF(ISNUMBER(N38),ROUND(N38/(1-Settings!$B$2)/Settings!$B$3,0)*Settings!$B$3,"") | T38: =IF(ISNUMBER(O38),ROUND(O38/(1-Settings!$B$2)/Settings!$B$3,0)*Settings!$B$3,"") | U38: =IF(ISNUMBER(P38),ROUND(P38/(1-Settings!$B$2)/Settings!$B$3,0)*Settings!$B$3,"") | V38: =IF(ISNUMBER(Q38),ROUND(Q38/(1-Settings!$B$2)/Settings!$B$3,0)*Settings!$B$3,"") | W38: 3860 | X38: 5945 | AC38: MasterMilitaryOnBaseList 12.2.25 NS.xlsx | AD38: Gate Marquees - Rucker_Specs.docx | AE38: Open in Box | AF38: Open in Box
A39: AL-FORTNOVO-016 | B39: Fort Novosel | D39: AL | E39: Montgomery | G39: Army | H39: Print & Publications | I39: Calendar Ad | K39: Your ad will appear in the installation events calendar. | L39: 1 | M39: 200 | R39: =IF(ISNUMBER(M39),ROUND(M39/(1-Settings!$B$2)/Settings!$B$3,0)*Settings!$B$3,"") | S39: =IF(ISNUMBER(N39),ROUND(N39/(1-Settings!$B$2)/Settings!$B$3,0)*Settings!$B$3,"") | T39: =IF(ISNUMBER(O39),ROUND(O39/(1-Settings!$B$2)/Settings!$B$3,0)*Settings!$B$3,"") | U39: =IF(ISNUMBER(P39),ROUND(P39/(1-Settings!$B$2)/Settings!$B$3,0)*Settings!$B$3,"") | V39: =IF(ISNUMBER(Q39),ROUND(Q39/(1-Settings!$B$2)/Settings!$B$3,0)*Settings!$B$3,"") | W39: 3860 | X39: 5945 | Y39: 2026 | Z39: 2026-06 | AC39: Military - National Publication Inventory Master_June 2026.xlsx | AD39: Gate Marquees - Rucker_Specs.docx | AE39: Open in Box | AF39: Open in Box
A40: AL-FORTNOVO-010 | B40: Fort Novosel | C40: Fort Rucker | D40: AL | E40: Montgomery | F40: 36322 | G40: Army | H40: Print & Publications | I40: Real Estate/Magazine Racks | K40: Your publication will be placed at one or more of the following locations on post (AAFES PX, Soldier Service Center, Silver Wings Golf Club, Shoppette/Mini Mall, Commissary, Lyster Health Clinic) *Price is per location | L40: 12 | P40: 250 | R40: =IF(ISNUMBER(M40),ROUND(M40/(1-Settings!$B$2)/Settings!$B$3,0)*Settings!$B$3,"") | S40: =IF(ISNUMBER(N40),ROUND(N40/(1-Settings!$B$2)/Settings!$B$3,0)*Settings!$B$3,"") | T40: =IF(ISNUMBER(O40),ROUND(O40/(1-Settings!$B$2)/Settings!$B$3,0)*Settings!$B$3,"") | U40: =IF(ISNUMBER(P40),ROUND(P40/(1-Settings!$B$2)/Settings!$B$3,0)*Settings!$B$3,"") | V40: =IF(ISNUMBER(Q40),ROUND(Q40/(1-Settings!$B$2)/Settings!$B$3,0)*Settings!$B$3,"") | W40: 3860 | X40: 5945 | AA40: Inventory master 6/2026 lists Magazine Ad at $1,200 (1 mo) | AC40: MasterMilitaryOnBaseList 12.2.25 NS.xlsx | AD40: Gate Marquees - Rucker_Specs.docx | AE40: Open in Box | AF40: Open in Box
A41: AL-FORTNOVO-014 | B41: Fort Novosel | C41: Fort Rucker | D41: AL | E41: Montgomery | F41: 36322 | G41: Army | H41: Sponsorship & Other | I41: Welcome Packet Ad | K41: Your ad will appear in the Fort Novosel Welcome Packet distributed to each soldier that attends the Newcomer's Welcome Briefing. | L41: 3 | N41: 200 | O41: 300 | P41: 500 | Q41: 0 | R41: =IF(ISNUMBER(M41),ROUND(M41/(1-Settings!$B$2)/Settings!$B$3,0)*Settings!$B$3,"") | S41: =IF(ISNUMBER(N41),ROUND(N41/(1-Settings!$B$2)/Settings!$B$3,0)*Settings!$B$3,"") | T41: =IF(ISNUMBER(O41),ROUND(O41/(1-Settings!$B$2)/Settings!$B$3,0)*Settings!$B$3,"") | U41: =IF(ISNUMBER(P41),ROUND(P41/(1-Settings!$B$2)/Settings!$B$3,0)*Settings!$B$3,"") | V41: =IF(ISNUMBER(Q41),ROUND(Q41/(1-Settings!$B$2)/Settings!$B$3,0)*Settings!$B$3,"") | W41: 3860 | X41: 5945 | AC41: MasterMilitaryOnBaseList 12.2.25 NS.xlsx | AD41: Gate Marquees - Rucker_Specs.docx | AE41: Open in Box | AF41: Open in Box
A42: AL-FORTNOVO-006 | B42: Fort Novosel | C42: Fort Rucker | D42: AL | E42: Montgomery | F42: 36322 | G42: Army | H42: Standard Media | I42: Outdoor Banner | J42: 4'W x 8'H | K42: Your signs will be placed on the fencing that surrounds the ball fields, Lake Tholocco, the Lemon Lot, and The Flightline. | L42: 1 | M42: 200 | N42: 600 | O42: 1200 | P42: 2400 | Q42: 200 | R42: =IF(ISNUMBER(M42),ROUND(M42/(1-Settings!$B$2)/Settings!$B$3,0)*Settings!$B$3,"") | S42: =IF(ISNUMBER(N42),ROUND(N42/(1-Settings!$B$2)/Settings!$B$3,0)*Settings!$B$3,"") | T42: =IF(ISNUMBER(O42),ROUND(O42/(1-Settings!$B$2)/Settings!$B$3,0)*Settings!$B$3,"") | U42: =IF(ISNUMBER(P42),ROUND(P42/(1-Settings!$B$2)/Settings!$B$3,0)*Settings!$B$3,"") | V42: =IF(ISNUMBER(Q42),ROUND(Q42/(1-Settings!$B$2)/Settings!$B$3,0)*Settings!$B$3,"") | W42: 3860 | X42: 5945 | AC42: MasterMilitaryOnBaseList 12.2.25 NS.xlsx | AD42: Gate Marquees - Rucker_Specs.docx | AE42: Open in Box | AF42: Open in Box
A43: AL-FORTNOVO-007 | B43: Fort Novosel | C43: Fort Rucker | D43: AL | E43: Montgomery | F43: 36322 | G43: Army | H43: Standard Media | I43: Outdoor Metal Sign | J43: 4'W x 8'H | K43: Your signs will be placed on the fencing that surrounds the ball fields, Lake Tholocco, the Lemon Lot, and The Flightline. | L43: 1 | M43: 200 | N43: 600 | O43: 1200 | P43: 2400 | Q43: 200 | R43: =IF(ISNUMBER(M43),ROUND(M43/(1-Settings!$B$2)/Settings!$B$3,0)*Settings!$B$3,"") | S43: =IF(ISNUMBER(N43),ROUND(N43/(1-Settings!$B$2)/Settings!$B$3,0)*Settings!$B$3,"") | T43: =IF(ISNUMBER(O43),ROUND(O43/(1-Settings!$B$2)/Settings!$B$3,0)*Settings!$B$3,"") | U43: =IF(ISNUMBER(P43),ROUND(P43/(1-Settings!$B$2)/Settings!$B$3,0)*Settings!$B$3,"") | V43: =IF(ISNUMBER(Q43),ROUND(Q43/(1-Settings!$B$2)/Settings!$B$3,0)*Settings!$B$3,"") | W43: 3860 | X43: 5945 | AC43: MasterMilitaryOnBaseList 12.2.25 NS.xlsx | AD43: Gate Marquees - Rucker_Specs.docx | AE43: Open in Box | AF43: Open in Box
A44: AL-FORTNOVO-008 | B44: Fort Novosel | C44: Fort Rucker | D44: AL | E44: Montgomery | F44: 36322 | G44: Army | H44: Standard Media | I44: Posters | K44: Your posters will be placed inside high traffic facilities and MWR program locations (building 5700 Soldier Service Center, AAFES PX, Lyster Army Medical Center, Shoppette, Center Library, Arts and Crafts Center, Physical Fitness Centers, Outdoor Recreation, The Flightline, Silver Wings Golf Club, Big Mike’s, Youth Center, and the Youth Fitness Center) | L44: 1 | M44: 100 | N44: 300 | O44: 600 | P44: 1200 | Q44: 100 | R44: =IF(ISNUMBER(M44),ROUND(M44/(1-Settings!$B$2)/Settings!$B$3,0)*Settings!$B$3,"") | S44: =IF(ISNUMBER(N44),ROUND(N44/(1-Settings!$B$2)/Settings!$B$3,0)*Settings!$B$3,"") | T44: =IF(ISNUMBER(O44),ROUND(O44/(1-Settings!$B$2)/Settings!$B$3,0)*Settings!$B$3,"") | U44: =IF(ISNUMBER(P44),ROUND(P44/(1-Settings!$B$2)/Settings!$B$3,0)*Settings!$B$3,"") | V44: =IF(ISNUMBER(Q44),ROUND(Q44/(1-Settings!$B$2)/Settings!$B$3,0)*Settings!$B$3,"") | W44: 3860 | X44: 5945 | AC44: MasterMilitaryOnBaseList 12.2.25 NS.xlsx | AD44: Gate Marquees - Rucker_Specs.docx | AE44: Open in Box | AF44: Open in Box
A45: AL-FORTNOVO-011 | B45: Fort Novosel | C45: Fort Rucker | D45: AL | E45: Montgomery | F45: 36322 | G45: Army | H45: Web & Email | I45: Facebook Page Exposure (1 post/week) | J45: 1080x1080px or higher | K45: Your ad will appear on Fort Novosel's Facebook page reaching an audience of 23,000 and growing including military soldiers, family members, civilians, and retirees. | L45: 1 | M45: 150 | N45: 450 | O45: 900 | P45: 1000 | Q45: 0 | R45: =IF(ISNUMBER(M45),ROUND(M45/(1-Settings!$B$2)/Settings!$B$3,0)*Settings!$B$3,"") | S45: =IF(ISNUMBER(N45),ROUND(N45/(1-Settings!$B$2)/Settings!$B$3,0)*Settings!$B$3,"") | T45: =IF(ISNUMBER(O45),ROUND(O45/(1-Settings!$B$2)/Settings!$B$3,0)*Settings!$B$3,"") | U45: =IF(ISNUMBER(P45),ROUND(P45/(1-Settings!$B$2)/Settings!$B$3,0)*Settings!$B$3,"") | V45: =IF(ISNUMBER(Q45),ROUND(Q45/(1-Settings!$B$2)/Settings!$B$3,0)*Settings!$B$3,"") | W45: 3860 | X45: 5945 | AC45: MasterMilitaryOnBaseList 12.2.25 NS.xlsx | AD45: Gate Marquees - Rucker_Specs.docx | AE45: Open in Box | AF45: Open in Box
A46: AL-FORTNOVO-012 | B46: Fort Novosel | C46: Fort Rucker | D46: AL | E46: Montgomery | F46: 36322 | G46: Army | H46: Web & Email | I46: Facebook Page Exposure (2 posts/week) | J46: 1080x1080px or higher | K46: Your ad will appear on Fort Novosel's Facebook page reaching an audience of 23,000 and growing including military soldiers, family members, civilians, and retirees. | L46: 1 | M46: 250 | N46: 750 | O46: 1500 | P46: 3000 | Q46: 0 | R46: =IF(ISNUMBER(M46),ROUND(M46/(1-Settings!$B$2)/Settings!$B$3,0)*Settings!$B$3,"") | S46: =IF(ISNUMBER(N46),ROUND(N46/(1-Settings!$B$2)/Settings!$B$3,0)*Settings!$B$3,"") | T46: =IF(ISNUMBER(O46),ROUND(O46/(1-Settings!$B$2)/Settings!$B$3,0)*Settings!$B$3,"") | U46: =IF(ISNUMBER(P46),ROUND(P46/(1-Settings!$B$2)/Settings!$B$3,0)*Settings!$B$3,"") | V46: =IF(ISNUMBER(Q46),ROUND(Q46/(1-Settings!$B$2)/Settings!$B$3,0)*Settings!$B$3,"") | W46: 3860 | X46: 5945 | AC46: MasterMilitaryOnBaseList 12.2.25 NS.xlsx | AD46: Gate Marquees - Rucker_Specs.docx | AE46: Open in Box | AF46: Open in Box
A47: AL-FORTNOVO-013 | B47: Fort Novosel | C47: Fort Rucker | D47: AL | E47: Montgomery | F47: 36322 | G47: Army | H47: Web & Email | I47: Facebook Page Exposure (3 posts/week) | J47: 1080x1080px or higher | K47: Your ad will appear on Fort Novosel's Facebook page reaching an audience of 23,000 and growing including military soldiers, family members, civilians, and retirees. | L47: 1 | M47: 325 | N47: 975 | O47: 1950 | P47: 3900 | Q47: 0 | R47: =IF(ISNUMBER(M47),ROUND(M47/(1-Settings!$B$2)/Settings!$B$3,0)*Settings!$B$3,"") | S47: =IF(ISNUMBER(N47),ROUND(N47/(1-Settings!$B$2)/Settings!$B$3,0)*Settings!$B$3,"") | T47: =IF(ISNUMBER(O47),ROUND(O47/(1-Settings!$B$2)/Settings!$B$3,0)*Settings!$B$3,"") | U47: =IF(ISNUMBER(P47),ROUND(P47/(1-Settings!$B$2)/Settings!$B$3,0)*Settings!$B$3,"") | V47: =IF(ISNUMBER(Q47),ROUND(Q47/(1-Settings!$B$2)/Settings!$B$3,0)*Settings!$B$3,"") | W47: 3860 | X47: 5945 | AC47: MasterMilitaryOnBaseList 12.2.25 NS.xlsx | AD47: Gate Marquees - Rucker_Specs.docx | AE47: Open in Box | AF47: Open in Box
A48: AL-FORTNOVO-015 | B48: Fort Novosel | D48: AL | E48: Montgomery | G48: Army | H48: Web & Email | I48: Weekly E-Newsletter Ad | K48: Your ad will appear in the weekly e-newsletter emailed to the installation community. | L48: 1 | M48: 250 | R48: =IF(ISNUMBER(M48),ROUND(M48/(1-Settings!$B$2)/Settings!$B$3,0)*Settings!$B$3,"") | S48: =IF(ISNUMBER(N48),ROUND(N48/(1-Settings!$B$2)/Settings!$B$3,0)*Settings!$B$3,"") | T48: =IF(ISNUMBER(O48),ROUND(O48/(1-Settings!$B$2)/Settings!$B$3,0)*Settings!$B$3,"") | U48: =IF(ISNUMBER(P48),ROUND(P48/(1-Settings!$B$2)/Settings!$B$3,0)*Settings!$B$3,"") | V48: =IF(ISNUMBER(Q48),ROUND(Q48/(1-Settings!$B$2)/Settings!$B$3,0)*Settings!$B$3,"") | W48: 3860 | X48: 5945 | Y48: 2026 | Z48: 2026-06 | AC48: Military - National Publication Inventory Master_June 2026.xlsx | AD48: Gate Marquees - Rucker_Specs.docx | AE48: Open in Box | AF48: Open in Box
A49: AL-MAXWELLA-001 | B49: Maxwell AFB (Incl. Gunter) | C49: Maxwell-Gunter AFB | D49: AL | E49: Montgomery-Selma | F49: 36112 | G49: Air Force | H49: Digital | I49: Bowling Center Monitors | K49: Your static ad will appear on 10 monitors in the on-base Gunter Lanes | L49: 3 | N49: 300 | O49: 500 | P49: 900 | Q49: 0 | R49: =IF(ISNUMBER(M49),ROUND(M49/(1-Settings!$B$2)/Settings!$B$3,0)*Settings!$B$3,"") | S49: =IF(ISNUMBER(N49),ROUND(N49/(1-Settings!$B$2)/Settings!$B$3,0)*Settings!$B$3,"") | T49: =IF(ISNUMBER(O49),ROUND(O49/(1-Settings!$B$2)/Settings!$B$3,0)*Settings!$B$3,"") | U49: =IF(ISNUMBER(P49),ROUND(P49/(1-Settings!$B$2)/Settings!$B$3,0)*Settings!$B$3,"") | V49: =IF(ISNUMBER(Q49),ROUND(Q49/(1-Settings!$B$2)/Settings!$B$3,0)*Settings!$B$3,"") | W49: 3012 | X49: 5336 | AB49: Source formula errors | AC49: MasterMilitaryOnBaseList 12.2.25 NS.xlsx | AD49: 2026 Advertising Rates.pdf | AE49: Open in Box | AF49: Open in Box
A50: AL-MAXWELLA-002 | B50: Maxwell AFB (Incl. Gunter) | C50: Maxwell-Gunter AFB | D50: AL | E50: Montgomery-Selma | F50: 36112 | G50: Air Force | H50: Digital | I50: Digital Kiosk Network | J50: 1080pxW x 1920pxH | K50: Your ad will appear on digital screens in high traffic areas on Maxwell and Gunter. (Screens located at the Airman & Family Readiness Center, Range 42 Bar & Grill, Maxwell Club and Event Center, Aviation Cadet Pool, Rickenbacker’s Coffee Shop, Hangar 42 Coffee Shop, University Inn/Lodging, Military Personnel Flight Section Lobbies, Outdoor Recreation Office, Fitness Centers, Child Development Centers, Maxwell and Gunter Youth Centers and Gunter Lanes) | L50: 1 | M50: 200 | N50: 500 | O50: 900 | P50: 1500 | Q50: 0 | R50: =IF(ISNUMBER(M50),ROUND(M50/(1-Settings!$B$2)/Settings!$B$3,0)*Settings!$B$3,"") | S50: =IF(ISNUMBER(N50),ROUND(N50/(1-Settings!$B$2)/Settings!$B$3,0)*Settings!$B$3,"") | T50: =IF(ISNUMBER(O50),ROUND(O50/(1-Settings!$B$2)/Settings!$B$3,0)*Settings!$B$3,"") | U50: =IF(ISNUMBER(P50),ROUND(P50/(1-Settings!$B$2)/Settings!$B$3,0)*Settings!$B$3,"") | V50: =IF(ISNUMBER(Q50),ROUND(Q50/(1-Settings!$B$2)/Settings!$B$3,0)*Settings!$B$3,"") | W50: 3012 | X50: 5336 | AC50: MasterMilitaryOnBaseList 12.2.25 NS.xlsx | AD50: 2026 Advertising Rates.pdf | AE50: Open in Box | AF50: Open in Box
A51: AL-MAXWELLA-003 | B51: Maxwell AFB (Incl. Gunter) | C51: Maxwell-Gunter AFB | D51: AL | E51: Montgomery-Selma | F51: 36112 | G51: Air Force | H51: Digital | I51: Digital Monitor Network | J51: 1632oxW x 864pxH | K51: Your ad will appear on digital screens in high traffic areas on Maxwell and Gunter. (Screens located at the Airman & Family Readiness Center, Range 42 Bar & Grill, Maxwell Club and Event Center, Aviation Cadet Pool, Rickenbacker’s Coffee Shop, Hangar 42 Coffee Shop, University Inn/Lodging, Military Personnel Flight Section Lobbies, Outdoor Recreation Office, Fitness Centers, Child Development Centers, Maxwell and Gunter Youth Centers and Gunter Lanes) | L51: 1 | M51: 200 | N51: 500 | O51: 900 | P51: 1500 | Q51: 0 | R51: =IF(ISNUMBER(M51),ROUND(M51/(1-Settings!$B$2)/Settings!$B$3,0)*Settings!$B$3,"") | S51: =IF(ISNUMBER(N51),ROUND(N51/(1-Settings!$B$2)/Settings!$B$3,0)*Settings!$B$3,"") | T51: =IF(ISNUMBER(O51),ROUND(O51/(1-Settings!$B$2)/Settings!$B$3,0)*Settings!$B$3,"") | U51: =IF(ISNUMBER(P51),ROUND(P51/(1-Settings!$B$2)/Settings!$B$3,0)*Settings!$B$3,"") | V51: =IF(ISNUMBER(Q51),ROUND(Q51/(1-Settings!$B$2)/Settings!$B$3,0)*Settings!$B$3,"") | W51: 3012 | X51: 5336 | AC51: MasterMilitaryOnBaseList 12.2.25 NS.xlsx | AD51: 2026 Advertising Rates.pdf | AE51: Open in Box | AF51: Open in Box
A52: AL-MAXWELLA-004 | B52: Maxwell AFB (Incl. Gunter) | C52: Maxwell-Gunter AFB | D52: AL | E52: Montgomery-Selma | F52: 36112 | G52: Air Force | H52: Print & Publications | I52: Weekly Newsletter Ad | J52: 580pxW x 325pxH | K52: Your ad will appear in the Life at the Max newsletter. Ad will contain a click-through link to the advertiser's website. Price is for 4 issues | L52: 1 | M52: 60 | N52: 180 | O52: 360 | P52: 720 | Q52: 0 | R52: =IF(ISNUMBER(M52),ROUND(M52/(1-Settings!$B$2)/Settings!$B$3,0)*Settings!$B$3,"") | S52: =IF(ISNUMBER(N52),ROUND(N52/(1-Settings!$B$2)/Settings!$B$3,0)*Settings!$B$3,"") | T52: =IF(ISNUMBER(O52),ROUND(O52/(1-Settings!$B$2)/Settings!$B$3,0)*Settings!$B$3,"") | U52: =IF(ISNUMBER(P52),ROUND(P52/(1-Settings!$B$2)/Settings!$B$3,0)*Settings!$B$3,"") | V52: =IF(ISNUMBER(Q52),ROUND(Q52/(1-Settings!$B$2)/Settings!$B$3,0)*Settings!$B$3,"") | W52: 3012 | X52: 5336 | AC52: MasterMilitaryOnBaseList 12.2.25 NS.xlsx | AD52: 2026 Advertising Rates.pdf | AE52: Open in Box | AF52: Open in Box
A53: AL-MAXWELLA-005 | B53: Maxwell AFB (Incl. Gunter) | D53: AL | E53: Montgomery-Selma | G53: Air Force | H53: Web & Email | I53: Web Ad | K53: Your ad will appear on the installation MWR / FSS website. | L53: 1 | M53: 200 | R53: =IF(ISNUMBER(M53),ROUND(M53/(1-Settings!$B$2)/Settings!$B$3,0)*Settings!$B$3,"") | S53: =IF(ISNUMBER(N53),ROUND(N53/(1-Settings!$B$2)/Settings!$B$3,0)*Settings!$B$3,"") | T53: =IF(ISNUMBER(O53),ROUND(O53/(1-Settings!$B$2)/Settings!$B$3,0)*Settings!$B$3,"") | U53: =IF(ISNUMBER(P53),ROUND(P53/(1-Settings!$B$2)/Settings!$B$3,0)*Settings!$B$3,"") | V53: =IF(ISNUMBER(Q53),ROUND(Q53/(1-Settings!$B$2)/Settings!$B$3,0)*Settings!$B$3,"") | W53: 3012 | X53: 5336 | Y53: 2026 | Z53: 2026-06 | AA53: Sent weekly, but price is per month | AC53: Military - National Publication Inventory Master_June 2026.xlsx | AD53: 2026 Advertising Rates.pdf | AE53: Open in Box | AF53: Open in Box
A54: AL-REDSTONE-001 | B54: Redstone Arsenal | D54: AL | E54: Huntsville-Decatur (Flor) | F54: 35898 | G54: Army | H54: Digital | I54: Bowling Scoring Monitors | K54: Your ad will appear on 32 digital bowling scoring monitors. | L54: 1 | M54: 1000 | N54: 2500 | O54: 4000 | P54: 6000 | Q54: 0 | R54: =IF(ISNUMBER(M54),ROUND(M54/(1-Settings!$B$2)/Settings!$B$3,0)*Settings!$B$3,"") | S54: =IF(ISNUMBER(N54),ROUND(N54/(1-Settings!$B$2)/Settings!$B$3,0)*Settings!$B$3,"") | T54: =IF(ISNUMBER(O54),ROUND(O54/(1-Settings!$B$2)/Settings!$B$3,0)*Settings!$B$3,"") | U54: =IF(ISNUMBER(P54),ROUND(P54/(1-Settings!$B$2)/Settings!$B$3,0)*Settings!$B$3,"") | V54: =IF(ISNUMBER(Q54),ROUND(Q54/(1-Settings!$B$2)/Settings!$B$3,0)*Settings!$B$3,"") | W54: 588 | X54: 1518 | AC54: MasterMilitaryOnBaseList 12.2.25 NS.xlsx | AD54: Gate 8 (Goss Road) Billboard Specs & Map.pdf | AE54: Open in Box | AF54: Open in Box
A55: AL-REDSTONE-002 | B55: Redstone Arsenal | D55: AL | E55: Huntsville-Decatur (Flor) | F55: 35898 | G55: Army | H55: Digital | I55: Digital Billboard Static Ad | J55: 200pxW x 500pxH | K55: Your ad will appear on the digital billboard located at Gate 9/Goss Road. | L55: 1 | M55: 3000 | N55: 4000 | O55: 8000 | P55: 16000 | Q55: 0 | R55: =IF(ISNUMBER(M55),ROUND(M55/(1-Settings!$B$2)/Settings!$B$3,0)*Settings!$B$3,"") | S55: =IF(ISNUMBER(N55),ROUND(N55/(1-Settings!$B$2)/Settings!$B$3,0)*Settings!$B$3,"") | T55: =IF(ISNUMBER(O55),ROUND(O55/(1-Settings!$B$2)/Settings!$B$3,0)*Settings!$B$3,"") | U55: =IF(ISNUMBER(P55),ROUND(P55/(1-Settings!$B$2)/Settings!$B$3,0)*Settings!$B$3,"") | V55: =IF(ISNUMBER(Q55),ROUND(Q55/(1-Settings!$B$2)/Settings!$B$3,0)*Settings!$B$3,"") | W55: 588 | X55: 1518 | AC55: MasterMilitaryOnBaseList 12.2.25 NS.xlsx | AD55: Gate 8 (Goss Road) Billboard Specs & Map.pdf | AE55: Open in Box | AF55: Open in Box
A56: AL-REDSTONE-003 | B56: Redstone Arsenal | D56: AL | E56: Huntsville-Decatur (Flor) | F56: 35898 | G56: Army | H56: Digital | I56: Digital Billboard Video Ad | J56: 30FPS / H.264 | K56: Your ad will appear on the digital billboard located at Gate 9/Goss Road. | L56: 1 | M56: 4000 | N56: 5000 | O56: 9000 | P56: 17000 | Q56: 0 | R56: =IF(ISNUMBER(M56),ROUND(M56/(1-Settings!$B$2)/Settings!$B$3,0)*Settings!$B$3,"") | S56: =IF(ISNUMBER(N56),ROUND(N56/(1-Settings!$B$2)/Settings!$B$3,0)*Settings!$B$3,"") | T56: =IF(ISNUMBER(O56),ROUND(O56/(1-Settings!$B$2)/Settings!$B$3,0)*Settings!$B$3,"") | U56: =IF(ISNUMBER(P56),ROUND(P56/(1-Settings!$B$2)/Settings!$B$3,0)*Settings!$B$3,"") | V56: =IF(ISNUMBER(Q56),ROUND(Q56/(1-Settings!$B$2)/Settings!$B$3,0)*Settings!$B$3,"") | W56: 588 | X56: 1518 | AC56: MasterMilitaryOnBaseList 12.2.25 NS.xlsx | AD56: Gate 8 (Goss Road) Billboard Specs & Map.pdf | AE56: Open in Box | AF56: Open in Box
A57: AL-REDSTONE-004 | B57: Redstone Arsenal | D57: AL | E57: Huntsville-Decatur (Flor) | F57: 35898 | G57: Army | H57: Digital | I57: Digital Monitor Network | J57: 1080pxW x 807pxW | K57: Your ad will appear on digital monitors in approved installation facilities. | L57: 1 | M57: 4000 | N57: 6000 | O57: 8000 | P57: 10000 | Q57: 0 | R57: =IF(ISNUMBER(M57),ROUND(M57/(1-Settings!$B$2)/Settings!$B$3,0)*Settings!$B$3,"") | S57: =IF(ISNUMBER(N57),ROUND(N57/(1-Settings!$B$2)/Settings!$B$3,0)*Settings!$B$3,"") | T57: =IF(ISNUMBER(O57),ROUND(O57/(1-Settings!$B$2)/Settings!$B$3,0)*Settings!$B$3,"") | U57: =IF(ISNUMBER(P57),ROUND(P57/(1-Settings!$B$2)/Settings!$B$3,0)*Settings!$B$3,"") | V57: =IF(ISNUMBER(Q57),ROUND(Q57/(1-Settings!$B$2)/Settings!$B$3,0)*Settings!$B$3,"") | W57: 588 | X57: 1518 | AC57: MasterMilitaryOnBaseList 12.2.25 NS.xlsx | AD57: Gate 8 (Goss Road) Billboard Specs & Map.pdf | AE57: Open in Box | AF57: Open in Box
A58: AL-REDSTONE-005 | B58: Redstone Arsenal | D58: AL | E58: Huntsville-Decatur (Flor) | F58: 35898 | G58: Army | H58: Digital | I58: Pin Sweeps | K58: Your ad will appear on 32 pin sweeps in the Redstone Bowling Lanes | L58: 6 | O58: 2500 | P58: 4000 | Q58: 0 | R58: =IF(ISNUMBER(M58),ROUND(M58/(1-Settings!$B$2)/Settings!$B$3,0)*Settings!$B$3,"") | S58: =IF(ISNUMBER(N58),ROUND(N58/(1-Settings!$B$2)/Settings!$B$3,0)*Settings!$B$3,"") | T58: =IF(ISNUMBER(O58),ROUND(O58/(1-Settings!$B$2)/Settings!$B$3,0)*Settings!$B$3,"") | U58: =IF(ISNUMBER(P58),ROUND(P58/(1-Settings!$B$2)/Settings!$B$3,0)*Settings!$B$3,"") | V58: =IF(ISNUMBER(Q58),ROUND(Q58/(1-Settings!$B$2)/Settings!$B$3,0)*Settings!$B$3,"") | W58: 588 | X58: 1518 | AC58: MasterMilitaryOnBaseList 12.2.25 NS.xlsx | AD58: Gate 8 (Goss Road) Billboard Specs & Map.pdf | AE58: Open in Box | AF58: Open in Box
A59: AL-REDSTONE-010 | B59: Redstone Arsenal | D59: AL | E59: Huntsville-Decatur (Flor) | F59: 35898 | G59: Army | H59: Large Format | I59: Beverage Cart Wraps | K59: Your ad will appear on a beverage cart wrap at The Links at Redstone | L59: 12 | P59: 5000 | Q59: 0 | R59: =IF(ISNUMBER(M59),ROUND(M59/(1-Settings!$B$2)/Settings!$B$3,0)*Settings!$B$3,"") | S59: =IF(ISNUMBER(N59),ROUND(N59/(1-Settings!$B$2)/Settings!$B$3,0)*Settings!$B$3,"") | T59: =IF(ISNUMBER(O59),ROUND(O59/(1-Settings!$B$2)/Settings!$B$3,0)*Settings!$B$3,"") | U59: =IF(ISNUMBER(P59),ROUND(P59/(1-Settings!$B$2)/Settings!$B$3,0)*Settings!$B$3,"") | V59: =IF(ISNUMBER(Q59),ROUND(Q59/(1-Settings!$B$2)/Settings!$B$3,0)*Settings!$B$3,"") | W59: 588 | X59: 1518 | AC59: MasterMilitaryOnBaseList 12.2.25 NS.xlsx | AD59: Gate 8 (Goss Road) Billboard Specs & Map.pdf | AE59: Open in Box | AF59: Open in Box
A60: AL-REDSTONE-011 | B60: Redstone Arsenal | D60: AL | E60: Huntsville-Decatur (Flor) | F60: 35898 | G60: Army | H60: Large Format | I60: Counter Wrap | J60: TBD | K60: Your ad will appear in an approved installation facility. | L60: 1 | M60: 3000 | N60: 4000 | O60: 6000 | P60: 8000 | R60: =IF(ISNUMBER(M60),ROUND(M60/(1-Settings!$B$2)/Settings!$B$3,0)*Settings!$B$3,"") | S60: =IF(ISNUMBER(N60),ROUND(N60/(1-Settings!$B$2)/Settings!$B$3,0)*Settings!$B$3,"") | T60: =IF(ISNUMBER(O60),ROUND(O60/(1-Settings!$B$2)/Settings!$B$3,0)*Settings!$B$3,"") | U60: =IF(ISNUMBER(P60),ROUND(P60/(1-Settings!$B$2)/Settings!$B$3,0)*Settings!$B$3,"") | V60: =IF(ISNUMBER(Q60),ROUND(Q60/(1-Settings!$B$2)/Settings!$B$3,0)*Settings!$B$3,"") | W60: 588 | X60: 1518 | AC60: MasterMilitaryOnBaseList 12.2.25 NS.xlsx | AD60: Gate 8 (Goss Road) Billboard Specs & Map.pdf | AE60: Open in Box | AF60: Open in Box
A61: AL-REDSTONE-012 | B61: Redstone Arsenal | D61: AL | E61: Huntsville-Decatur (Flor) | F61: 35898 | G61: Army | H61: Large Format | I61: Window Clings | K61: Your ad will appear in one location as a window cling. | L61: 12 | P61: 12000 | Q61: 0 | R61: =IF(ISNUMBER(M61),ROUND(M61/(1-Settings!$B$2)/Settings!$B$3,0)*Settings!$B$3,"") | S61: =IF(ISNUMBER(N61),ROUND(N61/(1-Settings!$B$2)/Settings!$B$3,0)*Settings!$B$3,"") | T61: =IF(ISNUMBER(O61),ROUND(O61/(1-Settings!$B$2)/Settings!$B$3,0)*Settings!$B$3,"") | U61: =IF(ISNUMBER(P61),ROUND(P61/(1-Settings!$B$2)/Settings!$B$3,0)*Settings!$B$3,"") | V61: =IF(ISNUMBER(Q61),ROUND(Q61/(1-Settings!$B$2)/Settings!$B$3,0)*Settings!$B$3,"") | W61: 588 | X61: 1518 | AC61: MasterMilitaryOnBaseList 12.2.25 NS.xlsx | AD61: Gate 8 (Goss Road) Billboard Specs & Map.pdf | AE61: Open in Box | AF61: Open in Box
A62: AL-REDSTONE-013 | B62: Redstone Arsenal | D62: AL | E62: Huntsville-Decatur (Flor) | F62: 35898 | G62: Army | H62: Print & Publications | I62: Brochure/Insert | K62: Your ad will appear in a brochure / flyer distributed at 4 approved installation facilities. | L62: 1 | M62: 800 | N62: 1200 | O62: 1600 | P62: 2000 | R62: =IF(ISNUMBER(M62),ROUND(M62/(1-Settings!$B$2)/Settings!$B$3,0)*Settings!$B$3,"") | S62: =IF(ISNUMBER(N62),ROUND(N62/(1-Settings!$B$2)/Settings!$B$3,0)*Settings!$B$3,"") | T62: =IF(ISNUMBER(O62),ROUND(O62/(1-Settings!$B$2)/Settings!$B$3,0)*Settings!$B$3,"") | U62: =IF(ISNUMBER(P62),ROUND(P62/(1-Settings!$B$2)/Settings!$B$3,0)*Settings!$B$3,"") | V62: =IF(ISNUMBER(Q62),ROUND(Q62/(1-Settings!$B$2)/Settings!$B$3,0)*Settings!$B$3,"") | W62: 588 | X62: 1518 | AC62: MasterMilitaryOnBaseList 12.2.25 NS.xlsx | AD62: Gate 8 (Goss Road) Billboard Specs & Map.pdf | AE62: Open in Box | AF62: Open in Box
A63: AL-REDSTONE-014 | B63: Redstone Arsenal | D63: AL | E63: Huntsville-Decatur (Flor) | F63: 35898 | G63: Army | H63: Sponsorship & Other | I63: Wi-Fi Splash Page | J63: 400pxW x 150pxH | K63: Your ad will appear on the Wi-Fi Splash Page which anyone accessing Wi-Fi on-base must visit. | L63: 1 | M63: 4000 | N63: 5000 | O63: 7000 | P63: 9000 | Q63: 0 | R63: =IF(ISNUMBER(M63),ROUND(M63/(1-Settings!$B$2)/Settings!$B$3,0)*Settings!$B$3,"") | S63: =IF(ISNUMBER(N63),ROUND(N63/(1-Settings!$B$2)/Settings!$B$3,0)*Settings!$B$3,"") | T63: =IF(ISNUMBER(O63),ROUND(O63/(1-Settings!$B$2)/Settings!$B$3,0)*Settings!$B$3,"") | U63: =IF(ISNUMBER(P63),ROUND(P63/(1-Settings!$B$2)/Settings!$B$3,0)*Settings!$B$3,"") | V63: =IF(ISNUMBER(Q63),ROUND(Q63/(1-Settings!$B$2)/Settings!$B$3,0)*Settings!$B$3,"") | W63: 588 | X63: 1518 | AC63: MasterMilitaryOnBaseList 12.2.25 NS.xlsx | AD63: Gate 8 (Goss Road) Billboard Specs & Map.pdf | AE63: Open in Box | AF63: Open in Box
A64: AL-REDSTONE-006 | B64: Redstone Arsenal | D64: AL | E64: Huntsville-Decatur (Flor) | F64: 35898 | G64: Army | H64: Standard Media | I64: Banner | J64: 3'x5' | K64: Your ad will appear in an approved installation facility. | L64: 1 | M64: 1000 | N64: 2000 | O64: 3000 | P64: 3000 | Q64: 200 | R64: =IF(ISNUMBER(M64),ROUND(M64/(1-Settings!$B$2)/Settings!$B$3,0)*Settings!$B$3,"") | S64: =IF(ISNUMBER(N64),ROUND(N64/(1-Settings!$B$2)/Settings!$B$3,0)*Settings!$B$3,"") | T64: =IF(ISNUMBER(O64),ROUND(O64/(1-Settings!$B$2)/Settings!$B$3,0)*Settings!$B$3,"") | U64: =IF(ISNUMBER(P64),ROUND(P64/(1-Settings!$B$2)/Settings!$B$3,0)*Settings!$B$3,"") | V64: =IF(ISNUMBER(Q64),ROUND(Q64/(1-Settings!$B$2)/Settings!$B$3,0)*Settings!$B$3,"") | W64: 588 | X64: 1518 | AC64: MasterMilitaryOnBaseList 12.2.25 NS.xlsx | AD64: Gate 8 (Goss Road) Billboard Specs & Map.pdf | AE64: Open in Box | AF64: Open in Box
A65: AL-REDSTONE-007 | B65: Redstone Arsenal | D65: AL | E65: Huntsville-Decatur (Flor) | F65: 35898 | G65: Army | H65: Standard Media | I65: Framed Poster | J65: 22"W x 28"H | K65: Your ad will appear in an approved installation facility. | L65: 1 | M65: 400 | N65: 800 | O65: 1000 | P65: 3000 | Q65: 100 | R65: =IF(ISNUMBER(M65),ROUND(M65/(1-Settings!$B$2)/Settings!$B$3,0)*Settings!$B$3,"") | S65: =IF(ISNUMBER(N65),ROUND(N65/(1-Settings!$B$2)/Settings!$B$3,0)*Settings!$B$3,"") | T65: =IF(ISNUMBER(O65),ROUND(O65/(1-Settings!$B$2)/Settings!$B$3,0)*Settings!$B$3,"") | U65: =IF(ISNUMBER(P65),ROUND(P65/(1-Settings!$B$2)/Settings!$B$3,0)*Settings!$B$3,"") | V65: =IF(ISNUMBER(Q65),ROUND(Q65/(1-Settings!$B$2)/Settings!$B$3,0)*Settings!$B$3,"") | W65: 588 | X65: 1518 | AC65: MasterMilitaryOnBaseList 12.2.25 NS.xlsx | AD65: Gate 8 (Goss Road) Billboard Specs & Map.pdf | AE65: Open in Box | AF65: Open in Box
A66: AL-REDSTONE-008 | B66: Redstone Arsenal | D66: AL | E66: Huntsville-Decatur (Flor) | F66: 35898 | G66: Army | H66: Standard Media | I66: Lightbox Advertisement | K66: Your ad will appear on a Lightbox Sign at an extrance or exit. | L66: 1 | M66: 1000 | N66: 2000 | O66: 3000 | P66: 4000 | Q66: 0 | R66: =IF(ISNUMBER(M66),ROUND(M66/(1-Settings!$B$2)/Settings!$B$3,0)*Settings!$B$3,"") | S66: =IF(ISNUMBER(N66),ROUND(N66/(1-Settings!$B$2)/Settings!$B$3,0)*Settings!$B$3,"") | T66: =IF(ISNUMBER(O66),ROUND(O66/(1-Settings!$B$2)/Settings!$B$3,0)*Settings!$B$3,"") | U66: =IF(ISNUMBER(P66),ROUND(P66/(1-Settings!$B$2)/Settings!$B$3,0)*Settings!$B$3,"") | V66: =IF(ISNUMBER(Q66),ROUND(Q66/(1-Settings!$B$2)/Settings!$B$3,0)*Settings!$B$3,"") | W66: 588 | X66: 1518 | AC66: MasterMilitaryOnBaseList 12.2.25 NS.xlsx | AD66: Gate 8 (Goss Road) Billboard Specs & Map.pdf | AE66: Open in Box | AF66: Open in Box
A67: AL-REDSTONE-009 | B67: Redstone Arsenal | D67: AL | E67: Huntsville-Decatur (Flor) | F67: 35898 | G67: Army | H67: Standard Media | I67: Tee Marker Set | J67: 12"W x 12"H | K67: Your ad will appear on a Tee Marker Set at The Links at Redstone | L67: 12 | P67: 2000 | R67: =IF(ISNUMBER(M67),ROUND(M67/(1-Settings!$B$2)/Settings!$B$3,0)*Settings!$B$3,"") | S67: =IF(ISNUMBER(N67),ROUND(N67/(1-Settings!$B$2)/Settings!$B$3,0)*Settings!$B$3,"") | T67: =IF(ISNUMBER(O67),ROUND(O67/(1-Settings!$B$2)/Settings!$B$3,0)*Settings!$B$3,"") | U67: =IF(ISNUMBER(P67),ROUND(P67/(1-Settings!$B$2)/Settings!$B$3,0)*Settings!$B$3,"") | V67: =IF(ISNUMBER(Q67),ROUND(Q67/(1-Settings!$B$2)/Settings!$B$3,0)*Settings!$B$3,"") | W67: 588 | X67: 1518 | AC67: MasterMilitaryOnBaseList 12.2.25 NS.xlsx | AD67: Gate 8 (Goss Road) Billboard Specs & Map.pdf | AE67: Open in Box | AF67: Open in Box
A68: AL-REDSTONE-016 | B68: Redstone Arsenal | D68: AL | E68: Huntsville-Decatur (Flor) | G68: Army | H68: Web & Email | I68: Web Ad | K68: Your ad will appear on the installation MWR / FSS website. | L68: 1 | M68: 800 | R68: =IF(ISNUMBER(M68),ROUND(M68/(1-Settings!$B$2)/Settings!$B$3,0)*Settings!$B$3,"") | S68: =IF(ISNUMBER(N68),ROUND(N68/(1-Settings!$B$2)/Settings!$B$3,0)*Settings!$B$3,"") | T68: =IF(ISNUMBER(O68),ROUND(O68/(1-Settings!$B$2)/Settings!$B$3,0)*Settings!$B$3,"") | U68: =IF(ISNUMBER(P68),ROUND(P68/(1-Settings!$B$2)/Settings!$B$3,0)*Settings!$B$3,"") | V68: =IF(ISNUMBER(Q68),ROUND(Q68/(1-Settings!$B$2)/Settings!$B$3,0)*Settings!$B$3,"") | W68: 588 | X68: 1518 | Y68: 2026 | Z68: 2026-06 | AA68: Sent weekly, but price is per month | AC68: Military - National Publication Inventory Master_June 2026.xlsx | AD68: Gate 8 (Goss Road) Billboard Specs & Map.pdf | AE68: Open in Box | AF68: Open in Box
A69: AL-REDSTONE-015 | B69: Redstone Arsenal | D69: AL | E69: Huntsville-Decatur (Flor) | G69: Army | H69: Web & Email | I69: Weekly E-Newsletter Ad | K69: Your ad will appear in the weekly e-newsletter emailed to the installation community. | L69: 1 | M69: 2500 | R69: =IF(ISNUMBER(M69),ROUND(M69/(1-Settings!$B$2)/Settings!$B$3,0)*Settings!$B$3,"") | S69: =IF(ISNUMBER(N69),ROUND(N69/(1-Settings!$B$2)/Settings!$B$3,0)*Settings!$B$3,"") | T69: =IF(ISNUMBER(O69),ROUND(O69/(1-Settings!$B$2)/Settings!$B$3,0)*Settings!$B$3,"") | U69: =IF(ISNUMBER(P69),ROUND(P69/(1-Settings!$B$2)/Settings!$B$3,0)*Settings!$B$3,"") | V69: =IF(ISNUMBER(Q69),ROUND(Q69/(1-Settings!$B$2)/Settings!$B$3,0)*Settings!$B$3,"") | W69: 588 | X69: 1518 | Y69: 2026 | Z69: 2026-06 | AA69: Sent weekly, but price is per month | AC69: Military - National Publication Inventory Master_June 2026.xlsx | AD69: Gate 8 (Goss Road) Billboard Specs & Map.pdf | AE69: Open in Box | AF69: Open in Box
A70: AR-FORTNOVO-001 | B70: Fort Novosel | C70: Fort Rucker | D70: AR | E70: Montgomery | F70: 36322 | G70: Army | H70: Print & Publications | I70: Welcome Guide Ad | J70: Full Page | K70: Your ad will appear in the Fort Novosel Family & MWR Welcome Guide distributed in all Family & MWR Facilities, Welcome Packets, Soldiers' units, Area Chambers of Commerce, and Welcome Centers. | L70: 12 | P70: 1800 | Q70: 0 | R70: =IF(ISNUMBER(M70),ROUND(M70/(1-Settings!$B$2)/Settings!$B$3,0)*Settings!$B$3,"") | S70: =IF(ISNUMBER(N70),ROUND(N70/(1-Settings!$B$2)/Settings!$B$3,0)*Settings!$B$3,"") | T70: =IF(ISNUMBER(O70),ROUND(O70/(1-Settings!$B$2)/Settings!$B$3,0)*Settings!$B$3,"") | U70: =IF(ISNUMBER(P70),ROUND(P70/(1-Settings!$B$2)/Settings!$B$3,0)*Settings!$B$3,"") | V70: =IF(ISNUMBER(Q70),ROUND(Q70/(1-Settings!$B$2)/Settings!$B$3,0)*Settings!$B$3,"") | W70: 3860 | X70: 5945 | AC70: MasterMilitaryOnBaseList 12.2.25 NS.xlsx | AD70: Gate Marquees - Rucker_Specs.docx | AE70: Open in Box | AF70: Open in Box
A71: AR-LITTLERO-001 | B71: Little Rock AFB | D71: AR | E71: Little Rock-Pine Bluff | F71: 72099 | G71: Air Force | H71: Digital | I71: Bowling Lane Sweepers | J71: Lanes 1-8: 44"W x 3.5"H, Lanes 9-24: 47.5"W x 4.5"H | K71: Your ad will appear on lane sweepers at the Little Rock AFB bowling center | L71: 3 | N71: 600 | O71: 800 | P71: 1600 | R71: =IF(ISNUMBER(M71),ROUND(M71/(1-Settings!$B$2)/Settings!$B$3,0)*Settings!$B$3,"") | S71: =IF(ISNUMBER(N71),ROUND(N71/(1-Settings!$B$2)/Settings!$B$3,0)*Settings!$B$3,"") | T71: =IF(ISNUMBER(O71),ROUND(O71/(1-Settings!$B$2)/Settings!$B$3,0)*Settings!$B$3,"") | U71: =IF(ISNUMBER(P71),ROUND(P71/(1-Settings!$B$2)/Settings!$B$3,0)*Settings!$B$3,"") | V71: =IF(ISNUMBER(Q71),ROUND(Q71/(1-Settings!$B$2)/Settings!$B$3,0)*Settings!$B$3,"") | W71: 3536 | X71: 4572 | AC71: MasterMilitaryOnBaseList 12.2.25 NS.xlsx | AD71: 2027_AdvertisingRateSheet.pdf | AE71: Open in Box | AF71: Open in Box
A72: AR-LITTLERO-002 | B72: Little Rock AFB | D72: AR | E72: Little Rock-Pine Bluff | F72: 72099 | G72: Air Force | H72: Digital | I72: Bowling Scoring Monitors | J72: 2775pxW x 1575pxH and 1080pxW x 1920pxH | K72: Your ad will appear on 48 digital scoring monitors. | L72: 1 | M72: 90 | N72: 255 | O72: 500 | P72: 1000 | R72: =IF(ISNUMBER(M72),ROUND(M72/(1-Settings!$B$2)/Settings!$B$3,0)*Settings!$B$3,"") | S72: =IF(ISNUMBER(N72),ROUND(N72/(1-Settings!$B$2)/Settings!$B$3,0)*Settings!$B$3,"") | T72: =IF(ISNUMBER(O72),ROUND(O72/(1-Settings!$B$2)/Settings!$B$3,0)*Settings!$B$3,"") | U72: =IF(ISNUMBER(P72),ROUND(P72/(1-Settings!$B$2)/Settings!$B$3,0)*Settings!$B$3,"") | V72: =IF(ISNUMBER(Q72),ROUND(Q72/(1-Settings!$B$2)/Settings!$B$3,0)*Settings!$B$3,"") | W72: 3536 | X72: 4572 | AC72: MasterMilitaryOnBaseList 12.2.25 NS.xlsx | AD72: 2027_AdvertisingRateSheet.pdf | AE72: Open in Box | AF72: Open in Box
A73: AR-LITTLERO-003 | B73: Little Rock AFB | D73: AR | E73: Little Rock-Pine Bluff | F73: 72099 | G73: Air Force | H73: Digital | I73: Bowling Special (Full service table tents, shoe ad s, and digital screen placement on the bowling alley monitors) | K73: Your ads will appear on table tents and bowling alley monitors and promo materials will be given away with rented shoes | L73: 3 | N73: 635 | O73: 845 | Q73: 0 | R73: =IF(ISNUMBER(M73),ROUND(M73/(1-Settings!$B$2)/Settings!$B$3,0)*Settings!$B$3,"") | S73: =IF(ISNUMBER(N73),ROUND(N73/(1-Settings!$B$2)/Settings!$B$3,0)*Settings!$B$3,"") | T73: =IF(ISNUMBER(O73),ROUND(O73/(1-Settings!$B$2)/Settings!$B$3,0)*Settings!$B$3,"") | U73: =IF(ISNUMBER(P73),ROUND(P73/(1-Settings!$B$2)/Settings!$B$3,0)*Settings!$B$3,"") | V73: =IF(ISNUMBER(Q73),ROUND(Q73/(1-Settings!$B$2)/Settings!$B$3,0)*Settings!$B$3,"") | W73: 3536 | X73: 4572 | AC73: MasterMilitaryOnBaseList 12.2.25 NS.xlsx | AD73: 2027_AdvertisingRateSheet.pdf | AE73: Open in Box | AF73: Open in Box
A74: AR-LITTLERO-004 | B74: Little Rock AFB | D74: AR | E74: Little Rock-Pine Bluff | F74: 72099 | G74: Air Force | H74: Digital | I74: Digital Monitor Network | J74: 2775pxW x 1575pxH and 1080pxW x 1920pxH | K74: Your ad will appear on digital monitors throughout the Little Rock AFB in high traffic areas | L74: 1 | M74: 440 | N74: 1300 | O74: 1500 | P74: 3000 | Q74: 0 | R74: =IF(ISNUMBER(M74),ROUND(M74/(1-Settings!$B$2)/Settings!$B$3,0)*Settings!$B$3,"") | S74: =IF(ISNUMBER(N74),ROUND(N74/(1-Settings!$B$2)/Settings!$B$3,0)*Settings!$B$3,"") | T74: =IF(ISNUMBER(O74),ROUND(O74/(1-Settings!$B$2)/Settings!$B$3,0)*Settings!$B$3,"") | U74: =IF(ISNUMBER(P74),ROUND(P74/(1-Settings!$B$2)/Settings!$B$3,0)*Settings!$B$3,"") | V74: =IF(ISNUMBER(Q74),ROUND(Q74/(1-Settings!$B$2)/Settings!$B$3,0)*Settings!$B$3,"") | W74: 3536 | X74: 4572 | AA74: Inventory master 6/2026 lists Digital Monitor Network at $715 (1 mo) | AC74: MasterMilitaryOnBaseList 12.2.25 NS.xlsx | AD74: 2027_AdvertisingRateSheet.pdf | AE74: Open in Box | AF74: Open in Box
A75: AR-LITTLERO-005 | B75: Little Rock AFB | D75: AR | E75: Little Rock-Pine Bluff | F75: 72099 | G75: Air Force | H75: Digital | I75: Lodging Digital Monitor Network | J75: 2,775W x 1,575H px (High res JPG or PDF, max of 300 dpi) | K75: Your ad will appear on monitors located in all 196 rooms across seven lodging buildings | L75: 1 | M75: 275 | N75: 800 | O75: 1500 | P75: 3000 | Q75: 0 | R75: =IF(ISNUMBER(M75),ROUND(M75/(1-Settings!$B$2)/Settings!$B$3,0)*Settings!$B$3,"") | S75: =IF(ISNUMBER(N75),ROUND(N75/(1-Settings!$B$2)/Settings!$B$3,0)*Settings!$B$3,"") | T75: =IF(ISNUMBER(O75),ROUND(O75/(1-Settings!$B$2)/Settings!$B$3,0)*Settings!$B$3,"") | U75: =IF(ISNUMBER(P75),ROUND(P75/(1-Settings!$B$2)/Settings!$B$3,0)*Settings!$B$3,"") | V75: =IF(ISNUMBER(Q75),ROUND(Q75/(1-Settings!$B$2)/Settings!$B$3,0)*Settings!$B$3,"") | W75: 3536 | X75: 4572 | AA75: Inventory master 6/2026 lists Digital Monitor Network at $715 (1 mo) | AC75: MasterMilitaryOnBaseList 12.2.25 NS.xlsx | AD75: 2027_AdvertisingRateSheet.pdf | AE75: Open in Box | AF75: Open in Box
A76: AR-LITTLERO-006 | B76: Little Rock AFB | D76: AR | E76: Little Rock-Pine Bluff | F76: 72099 | G76: Air Force | H76: Digital | I76: Shoe Rental Promotional materials (Full service) | K76: Your promotional materials will be handed out with every pair of bowling shoes rented (Full service: the Little Rock AFB team takes care of design, production, and ensures compliance) | L76: 1 | M76: 215 | N76: 385 | O76: 595 | P76: 1190 | R76: =IF(ISNUMBER(M76),ROUND(M76/(1-Settings!$B$2)/Settings!$B$3,0)*Settings!$B$3,"") | S76: =IF(ISNUMBER(N76),ROUND(N76/(1-Settings!$B$2)/Settings!$B$3,0)*Settings!$B$3,"") | T76: =IF(ISNUMBER(O76),ROUND(O76/(1-Settings!$B$2)/Settings!$B$3,0)*Settings!$B$3,"") | U76: =IF(ISNUMBER(P76),ROUND(P76/(1-Settings!$B$2)/Settings!$B$3,0)*Settings!$B$3,"") | V76: =IF(ISNUMBER(Q76),ROUND(Q76/(1-Settings!$B$2)/Settings!$B$3,0)*Settings!$B$3,"") | W76: 3536 | X76: 4572 | AC76: MasterMilitaryOnBaseList 12.2.25 NS.xlsx | AD76: 2027_AdvertisingRateSheet.pdf | AE76: Open in Box | AF76: Open in Box
A77: AR-LITTLERO-010 | B77: Little Rock AFB | D77: AR | E77: Little Rock-Pine Bluff | F77: 72099 | G77: Air Force | H77: Large Format | I77: Counter Wrap (Auto Hobby) | K77: Your ad will appear on a counter wrap in the Auto Hobby facility | L77: 12 | P77: 1500 | R77: =IF(ISNUMBER(M77),ROUND(M77/(1-Settings!$B$2)/Settings!$B$3,0)*Settings!$B$3,"") | S77: =IF(ISNUMBER(N77),ROUND(N77/(1-Settings!$B$2)/Settings!$B$3,0)*Settings!$B$3,"") | T77: =IF(ISNUMBER(O77),ROUND(O77/(1-Settings!$B$2)/Settings!$B$3,0)*Settings!$B$3,"") | U77: =IF(ISNUMBER(P77),ROUND(P77/(1-Settings!$B$2)/Settings!$B$3,0)*Settings!$B$3,"") | V77: =IF(ISNUMBER(Q77),ROUND(Q77/(1-Settings!$B$2)/Settings!$B$3,0)*Settings!$B$3,"") | W77: 3536 | X77: 4572 | AC77: MasterMilitaryOnBaseList 12.2.25 NS.xlsx | AD77: 2027_AdvertisingRateSheet.pdf | AE77: Open in Box | AF77: Open in Box
A78: AR-LITTLERO-011 | B78: Little Rock AFB | D78: AR | E78: Little Rock-Pine Bluff | F78: 72099 | G78: Air Force | H78: Large Format | I78: Counter Wrap (Fitness Center) | K78: Your ad will appear on a counter wrap in the Little Rock AFB Fitness Center | L78: 12 | P78: 3000 | R78: =IF(ISNUMBER(M78),ROUND(M78/(1-Settings!$B$2)/Settings!$B$3,0)*Settings!$B$3,"") | S78: =IF(ISNUMBER(N78),ROUND(N78/(1-Settings!$B$2)/Settings!$B$3,0)*Settings!$B$3,"") | T78: =IF(ISNUMBER(O78),ROUND(O78/(1-Settings!$B$2)/Settings!$B$3,0)*Settings!$B$3,"") | U78: =IF(ISNUMBER(P78),ROUND(P78/(1-Settings!$B$2)/Settings!$B$3,0)*Settings!$B$3,"") | V78: =IF(ISNUMBER(Q78),ROUND(Q78/(1-Settings!$B$2)/Settings!$B$3,0)*Settings!$B$3,"") | W78: 3536 | X78: 4572 | AC78: MasterMilitaryOnBaseList 12.2.25 NS.xlsx | AD78: 2027_AdvertisingRateSheet.pdf | AE78: Open in Box | AF78: Open in Box
A79: AR-LITTLERO-012 | B79: Little Rock AFB | D79: AR | E79: Little Rock-Pine Bluff | F79: 72099 | G79: Air Force | H79: Large Format | I79: Counter Wrap (Hangar 1080) | K79: Your ad will appear on a counter wrap in Hangar 1080 | L79: 12 | P79: 1500 | R79: =IF(ISNUMBER(M79),ROUND(M79/(1-Settings!$B$2)/Settings!$B$3,0)*Settings!$B$3,"") | S79: =IF(ISNUMBER(N79),ROUND(N79/(1-Settings!$B$2)/Settings!$B$3,0)*Settings!$B$3,"") | T79: =IF(ISNUMBER(O79),ROUND(O79/(1-Settings!$B$2)/Settings!$B$3,0)*Settings!$B$3,"") | U79: =IF(ISNUMBER(P79),ROUND(P79/(1-Settings!$B$2)/Settings!$B$3,0)*Settings!$B$3,"") | V79: =IF(ISNUMBER(Q79),ROUND(Q79/(1-Settings!$B$2)/Settings!$B$3,0)*Settings!$B$3,"") | W79: 3536 | X79: 4572 | AC79: MasterMilitaryOnBaseList 12.2.25 NS.xlsx | AD79: 2027_AdvertisingRateSheet.pdf | AE79: Open in Box | AF79: Open in Box
A80: AR-LITTLERO-013 | B80: Little Rock AFB | D80: AR | E80: Little Rock-Pine Bluff | F80: 72099 | G80: Air Force | H80: Large Format | I80: Counter Wrap (Outdoor Recreation) | K80: Your ad will appear on a counter wrap in the Little Rock AFB Outdoor Recreation facility | L80: 12 | P80: 1500 | R80: =IF(ISNUMBER(M80),ROUND(M80/(1-Settings!$B$2)/Settings!$B$3,0)*Settings!$B$3,"") | S80: =IF(ISNUMBER(N80),ROUND(N80/(1-Settings!$B$2)/Settings!$B$3,0)*Settings!$B$3,"") | T80: =IF(ISNUMBER(O80),ROUND(O80/(1-Settings!$B$2)/Settings!$B$3,0)*Settings!$B$3,"") | U80: =IF(ISNUMBER(P80),ROUND(P80/(1-Settings!$B$2)/Settings!$B$3,0)*Settings!$B$3,"") | V80: =IF(ISNUMBER(Q80),ROUND(Q80/(1-Settings!$B$2)/Settings!$B$3,0)*Settings!$B$3,"") | W80: 3536 | X80: 4572 | AC80: MasterMilitaryOnBaseList 12.2.25 NS.xlsx | AD80: 2027_AdvertisingRateSheet.pdf | AE80: Open in Box | AF80: Open in Box
A81: AR-LITTLERO-014 | B81: Little Rock AFB | D81: AR | E81: Little Rock-Pine Bluff | F81: 72099 | G81: Air Force | H81: Large Format | I81: Window Clings (Fitness Center) | K81: Your ad will appear on a window cling on the Fitness Center front door | L81: 3 | N81: 350 | O81: 700 | P81: 1400 | R81: =IF(ISNUMBER(M81),ROUND(M81/(1-Settings!$B$2)/Settings!$B$3,0)*Settings!$B$3,"") | S81: =IF(ISNUMBER(N81),ROUND(N81/(1-Settings!$B$2)/Settings!$B$3,0)*Settings!$B$3,"") | T81: =IF(ISNUMBER(O81),ROUND(O81/(1-Settings!$B$2)/Settings!$B$3,0)*Settings!$B$3,"") | U81: =IF(ISNUMBER(P81),ROUND(P81/(1-Settings!$B$2)/Settings!$B$3,0)*Settings!$B$3,"") | V81: =IF(ISNUMBER(Q81),ROUND(Q81/(1-Settings!$B$2)/Settings!$B$3,0)*Settings!$B$3,"") | W81: 3536 | X81: 4572 | AC81: MasterMilitaryOnBaseList 12.2.25 NS.xlsx | AD81: 2027_AdvertisingRateSheet.pdf | AE81: Open in Box | AF81: Open in Box
A82: AR-LITTLERO-015 | B82: Little Rock AFB | D82: AR | E82: Little Rock-Pine Bluff | F82: 72099 | G82: Air Force | H82: Large Format | I82: Window Clings (Outdoor Recreation) | K82: Your ad will appear on a window cling on the Outdoor Recreation front door | L82: 3 | N82: 200 | O82: 400 | P82: 800 | R82: =IF(ISNUMBER(M82),ROUND(M82/(1-Settings!$B$2)/Settings!$B$3,0)*Settings!$B$3,"") | S82: =IF(ISNUMBER(N82),ROUND(N82/(1-Settings!$B$2)/Settings!$B$3,0)*Settings!$B$3,"") | T82: =IF(ISNUMBER(O82),ROUND(O82/(1-Settings!$B$2)/Settings!$B$3,0)*Settings!$B$3,"") | U82: =IF(ISNUMBER(P82),ROUND(P82/(1-Settings!$B$2)/Settings!$B$3,0)*Settings!$B$3,"") | V82: =IF(ISNUMBER(Q82),ROUND(Q82/(1-Settings!$B$2)/Settings!$B$3,0)*Settings!$B$3,"") | W82: 3536 | X82: 4572 | AC82: MasterMilitaryOnBaseList 12.2.25 NS.xlsx | AD82: 2027_AdvertisingRateSheet.pdf | AE82: Open in Box | AF82: Open in Box
A83: AR-LITTLERO-016 | B83: Little Rock AFB | D83: AR | E83: Little Rock-Pine Bluff | F83: 72099 | G83: Air Force | H83: Large Format | I83: Window Clings (Skills Center) | K83: Your ad will appear on a window cling on the Skills Center front door | L83: 3 | N83: 200 | O83: 400 | P83: 800 | R83: =IF(ISNUMBER(M83),ROUND(M83/(1-Settings!$B$2)/Settings!$B$3,0)*Settings!$B$3,"") | S83: =IF(ISNUMBER(N83),ROUND(N83/(1-Settings!$B$2)/Settings!$B$3,0)*Settings!$B$3,"") | T83: =IF(ISNUMBER(O83),ROUND(O83/(1-Settings!$B$2)/Settings!$B$3,0)*Settings!$B$3,"") | U83: =IF(ISNUMBER(P83),ROUND(P83/(1-Settings!$B$2)/Settings!$B$3,0)*Settings!$B$3,"") | V83: =IF(ISNUMBER(Q83),ROUND(Q83/(1-Settings!$B$2)/Settings!$B$3,0)*Settings!$B$3,"") | W83: 3536 | X83: 4572 | AC83: MasterMilitaryOnBaseList 12.2.25 NS.xlsx | AD83: 2027_AdvertisingRateSheet.pdf | AE83: Open in Box | AF83: Open in Box
A84: AR-LITTLERO-018 | B84: Little Rock AFB | D84: AR | E84: Little Rock-Pine Bluff | F84: 72099 | G84: Air Force | H84: Sponsorship & Other | I84: Newcomers Orientation Promo Materials | K84: Your promotional materials (ranging from pamphlets to brand-labelled goodies) will be given out to new Airmen and their families at the bi-weekly newcomers orientations | L84: 3 | N84: 300 | O84: 500 | P84: 800 | R84: =IF(ISNUMBER(M84),ROUND(M84/(1-Settings!$B$2)/Settings!$B$3,0)*Settings!$B$3,"") | S84: =IF(ISNUMBER(N84),ROUND(N84/(1-Settings!$B$2)/Settings!$B$3,0)*Settings!$B$3,"") | T84: =IF(ISNUMBER(O84),ROUND(O84/(1-Settings!$B$2)/Settings!$B$3,0)*Settings!$B$3,"") | U84: =IF(ISNUMBER(P84),ROUND(P84/(1-Settings!$B$2)/Settings!$B$3,0)*Settings!$B$3,"") | V84: =IF(ISNUMBER(Q84),ROUND(Q84/(1-Settings!$B$2)/Settings!$B$3,0)*Settings!$B$3,"") | W84: 3536 | X84: 4572 | AC84: MasterMilitaryOnBaseList 12.2.25 NS.xlsx | AD84: 2027_AdvertisingRateSheet.pdf | AE84: Open in Box | AF84: Open in Box
A85: AR-LITTLERO-007 | B85: Little Rock AFB | D85: AR | E85: Little Rock-Pine Bluff | F85: 72099 | G85: Air Force | H85: Standard Media | I85: Banners | J85: 6'W x 3'H | K85: Your ad will appear at an approved installation facility. | L85: 1 | M85: 140 | N85: 275 | O85: 500 | P85: 1000 | Q85: 200 | R85: =IF(ISNUMBER(M85),ROUND(M85/(1-Settings!$B$2)/Settings!$B$3,0)*Settings!$B$3,"") | S85: =IF(ISNUMBER(N85),ROUND(N85/(1-Settings!$B$2)/Settings!$B$3,0)*Settings!$B$3,"") | T85: =IF(ISNUMBER(O85),ROUND(O85/(1-Settings!$B$2)/Settings!$B$3,0)*Settings!$B$3,"") | U85: =IF(ISNUMBER(P85),ROUND(P85/(1-Settings!$B$2)/Settings!$B$3,0)*Settings!$B$3,"") | V85: =IF(ISNUMBER(Q85),ROUND(Q85/(1-Settings!$B$2)/Settings!$B$3,0)*Settings!$B$3,"") | W85: 3536 | X85: 4572 | AC85: MasterMilitaryOnBaseList 12.2.25 NS.xlsx | AD85: 2027_AdvertisingRateSheet.pdf | AE85: Open in Box | AF85: Open in Box
A86: AR-LITTLERO-008 | B86: Little Rock AFB | D86: AR | E86: Little Rock-Pine Bluff | F86: 72099 | G86: Air Force | H86: Standard Media | I86: Posters | J86: 24"W x 29"H | K86: Your ad will appear at an approved installation facility. | L86: 1 | M86: 140 | N86: 275 | O86: 500 | P86: 1000 | Q86: 100 | R86: =IF(ISNUMBER(M86),ROUND(M86/(1-Settings!$B$2)/Settings!$B$3,0)*Settings!$B$3,"") | S86: =IF(ISNUMBER(N86),ROUND(N86/(1-Settings!$B$2)/Settings!$B$3,0)*Settings!$B$3,"") | T86: =IF(ISNUMBER(O86),ROUND(O86/(1-Settings!$B$2)/Settings!$B$3,0)*Settings!$B$3,"") | U86: =IF(ISNUMBER(P86),ROUND(P86/(1-Settings!$B$2)/Settings!$B$3,0)*Settings!$B$3,"") | V86: =IF(ISNUMBER(Q86),ROUND(Q86/(1-Settings!$B$2)/Settings!$B$3,0)*Settings!$B$3,"") | W86: 3536 | X86: 4572 | AC86: MasterMilitaryOnBaseList 12.2.25 NS.xlsx | AD86: 2027_AdvertisingRateSheet.pdf | AE86: Open in Box | AF86: Open in Box
A87: AR-LITTLERO-009 | B87: Little Rock AFB | D87: AR | E87: Little Rock-Pine Bluff | F87: 72099 | G87: Air Force | H87: Standard Media | I87: Table Tents (Full Service) | K87: Your ad will appear on table tents on every table in the bowling alley (Full Service: the Little Rock AFB team takes care of design, table tents, and ensures compliance) | L87: 1 | M87: 220 | N87: 390 | O87: 600 | P87: 1200 | R87: =IF(ISNUMBER(M87),ROUND(M87/(1-Settings!$B$2)/Settings!$B$3,0)*Settings!$B$3,"") | S87: =IF(ISNUMBER(N87),ROUND(N87/(1-Settings!$B$2)/Settings!$B$3,0)*Settings!$B$3,"") | T87: =IF(ISNUMBER(O87),ROUND(O87/(1-Settings!$B$2)/Settings!$B$3,0)*Settings!$B$3,"") | U87: =IF(ISNUMBER(P87),ROUND(P87/(1-Settings!$B$2)/Settings!$B$3,0)*Settings!$B$3,"") | V87: =IF(ISNUMBER(Q87),ROUND(Q87/(1-Settings!$B$2)/Settings!$B$3,0)*Settings!$B$3,"") | W87: 3536 | X87: 4572 | AC87: MasterMilitaryOnBaseList 12.2.25 NS.xlsx | AD87: 2027_AdvertisingRateSheet.pdf | AE87: Open in Box | AF87: Open in Box
A88: AR-LITTLERO-017 | B88: Little Rock AFB | D88: AR | E88: Little Rock-Pine Bluff | F88: 72099 | G88: Air Force | H88: Web & Email | I88: E-Newsletter | J88: 728W x 210H px (High res JPG or PDF, max of 150 dpi) | K88: Your ad will appear in the "Rockin' Rundown" E-Newsletter, sent out on a weekly basis | L88: 1 | M88: 150 | N88: 320 | O88: 530 | P88: 1060 | Q88: 0 | R88: =IF(ISNUMBER(M88),ROUND(M88/(1-Settings!$B$2)/Settings!$B$3,0)*Settings!$B$3,"") | S88: =IF(ISNUMBER(N88),ROUND(N88/(1-Settings!$B$2)/Settings!$B$3,0)*Settings!$B$3,"") | T88: =IF(ISNUMBER(O88),ROUND(O88/(1-Settings!$B$2)/Settings!$B$3,0)*Settings!$B$3,"") | U88: =IF(ISNUMBER(P88),ROUND(P88/(1-Settings!$B$2)/Settings!$B$3,0)*Settings!$B$3,"") | V88: =IF(ISNUMBER(Q88),ROUND(Q88/(1-Settings!$B$2)/Settings!$B$3,0)*Settings!$B$3,"") | W88: 3536 | X88: 4572 | AC88: MasterMilitaryOnBaseList 12.2.25 NS.xlsx | AD88: 2027_AdvertisingRateSheet.pdf | AE88: Open in Box | AF88: Open in Box
A89: AR-LITTLERO-019 | B89: Little Rock AFB | D89: AR | E89: Little Rock-Pine Bluff | G89: Air Force | H89: Web & Email | I89: Web Ad | K89: Your ad will appear on the installation MWR / FSS website. | L89: 1 | M89: 200 | R89: =IF(ISNUMBER(M89),ROUND(M89/(1-Settings!$B$2)/Settings!$B$3,0)*Settings!$B$3,"") | S89: =IF(ISNUMBER(N89),ROUND(N89/(1-Settings!$B$2)/Settings!$B$3,0)*Settings!$B$3,"") | T89: =IF(ISNUMBER(O89),ROUND(O89/(1-Settings!$B$2)/Settings!$B$3,0)*Settings!$B$3,"") | U89: =IF(ISNUMBER(P89),ROUND(P89/(1-Settings!$B$2)/Settings!$B$3,0)*Settings!$B$3,"") | V89: =IF(ISNUMBER(Q89),ROUND(Q89/(1-Settings!$B$2)/Settings!$B$3,0)*Settings!$B$3,"") | W89: 3536 | X89: 4572 | Y89: 2026 | Z89: 2026-06 | AC89: Military - National Publication Inventory Master_June 2026.xlsx | AD89: 2027_AdvertisingRateSheet.pdf | AE89: Open in Box | AF89: Open in Box
A90: AZ-DAVISMON-001 | B90: Davis-Monthan Air Force Base | D90: AZ | E90: Tucson (Sierra Vista), AZ | G90: Air Force | H90: Digital | I90: Digital Monitor Network | J90: 12 screens | K90: Your ad will appear on the 12-screen digital monitor network in approved installation facilities. | L90: 1 | M90: 2500 | R90: =IF(ISNUMBER(M90),ROUND(M90/(1-Settings!$B$2)/Settings!$B$3,0)*Settings!$B$3,"") | S90: =IF(ISNUMBER(N90),ROUND(N90/(1-Settings!$B$2)/Settings!$B$3,0)*Settings!$B$3,"") | T90: =IF(ISNUMBER(O90),ROUND(O90/(1-Settings!$B$2)/Settings!$B$3,0)*Settings!$B$3,"") | U90: =IF(ISNUMBER(P90),ROUND(P90/(1-Settings!$B$2)/Settings!$B$3,0)*Settings!$B$3,"") | V90: =IF(ISNUMBER(Q90),ROUND(Q90/(1-Settings!$B$2)/Settings!$B$3,0)*Settings!$B$3,"") | W90: 5995 | X90: 6924 | Y90: 2026 | Z90: 2026-06 | AC90: Military - National Digital Inventory Master 6.3.26.xlsx | AD90: 2026 Advertising Rates.pptx | AE90: Open in Box | AF90: Open in Box
A91: AZ-DAVISMON-003 | B91: Davis-Monthan Air Force Base | D91: AZ | E91: Tucson (Sierra Vista), AZ | G91: Air Force | H91: Print & Publications | I91: Magazine Ad | K91: Your ad will appear in the installation magazine. | L91: 3 | N91: 450 | R91: =IF(ISNUMBER(M91),ROUND(M91/(1-Settings!$B$2)/Settings!$B$3,0)*Settings!$B$3,"") | S91: =IF(ISNUMBER(N91),ROUND(N91/(1-Settings!$B$2)/Settings!$B$3,0)*Settings!$B$3,"") | T91: =IF(ISNUMBER(O91),ROUND(O91/(1-Settings!$B$2)/Settings!$B$3,0)*Settings!$B$3,"") | U91: =IF(ISNUMBER(P91),ROUND(P91/(1-Settings!$B$2)/Settings!$B$3,0)*Settings!$B$3,"") | V91: =IF(ISNUMBER(Q91),ROUND(Q91/(1-Settings!$B$2)/Settings!$B$3,0)*Settings!$B$3,"") | W91: 5995 | X91: 6924 | Y91: 2026 | Z91: 2026-06 | AA91: 3-month commitment | AC91: Military - National Publication Inventory Master_June 2026.xlsx | AD91: 2026 Advertising Rates.pptx | AE91: Open in Box | AF91: Open in Box
A92: AZ-DAVISMON-002 | B92: Davis-Monthan Air Force Base | D92: AZ | E92: Tucson (Sierra Vista), AZ | G92: Air Force | H92: Web & Email | I92: Web Ad | K92: Your ad will appear on the installation MWR / FSS website. | L92: 3 | N92: 375 | R92: =IF(ISNUMBER(M92),ROUND(M92/(1-Settings!$B$2)/Settings!$B$3,0)*Settings!$B$3,"") | S92: =IF(ISNUMBER(N92),ROUND(N92/(1-Settings!$B$2)/Settings!$B$3,0)*Settings!$B$3,"") | T92: =IF(ISNUMBER(O92),ROUND(O92/(1-Settings!$B$2)/Settings!$B$3,0)*Settings!$B$3,"") | U92: =IF(ISNUMBER(P92),ROUND(P92/(1-Settings!$B$2)/Settings!$B$3,0)*Settings!$B$3,"") | V92: =IF(ISNUMBER(Q92),ROUND(Q92/(1-Settings!$B$2)/Settings!$B$3,0)*Settings!$B$3,"") | W92: 5995 | X92: 6924 | Y92: 2026 | Z92: 2026-06 | AA92: 3-month commitment | AC92: Military - National Publication Inventory Master_June 2026.xlsx | AD92: 2026 Advertising Rates.pptx | AE92: Open in Box | AF92: Open in Box
A93: AZ-FORTHUAC-001 | B93: Fort Huachuca | D93: AZ | E93: Tucson (Sierra Vista), AZ | G93: Army | H93: Digital | I93: Bowling Scoring Monitors | J93: 24 screens | K93: Your ad will appear on the 24-screen scoring monitors in the installation bowling center. | L93: 1 | M93: 150 | R93: =IF(ISNUMBER(M93),ROUND(M93/(1-Settings!$B$2)/Settings!$B$3,0)*Settings!$B$3,"") | S93: =IF(ISNUMBER(N93),ROUND(N93/(1-Settings!$B$2)/Settings!$B$3,0)*Settings!$B$3,"") | T93: =IF(ISNUMBER(O93),ROUND(O93/(1-Settings!$B$2)/Settings!$B$3,0)*Settings!$B$3,"") | U93: =IF(ISNUMBER(P93),ROUND(P93/(1-Settings!$B$2)/Settings!$B$3,0)*Settings!$B$3,"") | V93: =IF(ISNUMBER(Q93),ROUND(Q93/(1-Settings!$B$2)/Settings!$B$3,0)*Settings!$B$3,"") | W93: 4139 | X93: 5163 | Y93: 2026 | Z93: 2026-06 | AC93: Military - National Digital Inventory Master 6.3.26.xlsx | AD93: 2026_Rate_Card.pdf | AE93: Open in Box | AF93: Open in Box
A94: AZ-FORTHUAC-003 | B94: Fort Huachuca | D94: AZ | E94: Tucson (Sierra Vista), AZ | G94: Army | H94: Print & Publications | I94: Magazine Ad | K94: Your ad will appear in the installation magazine. | L94: 12 | P94: 600 | R94: =IF(ISNUMBER(M94),ROUND(M94/(1-Settings!$B$2)/Settings!$B$3,0)*Settings!$B$3,"") | S94: =IF(ISNUMBER(N94),ROUND(N94/(1-Settings!$B$2)/Settings!$B$3,0)*Settings!$B$3,"") | T94: =IF(ISNUMBER(O94),ROUND(O94/(1-Settings!$B$2)/Settings!$B$3,0)*Settings!$B$3,"") | U94: =IF(ISNUMBER(P94),ROUND(P94/(1-Settings!$B$2)/Settings!$B$3,0)*Settings!$B$3,"") | V94: =IF(ISNUMBER(Q94),ROUND(Q94/(1-Settings!$B$2)/Settings!$B$3,0)*Settings!$B$3,"") | W94: 4139 | X94: 5163 | Y94: 2026 | Z94: 2026-06 | AA94: Sold annually; Magazine printed quarterly | AC94: Military - National Publication Inventory Master_June 2026.xlsx | AD94: 2026_Rate_Card.pdf | AE94: Open in Box | AF94: Open in Box
A95: AZ-FORTHUAC-002 | B95: Fort Huachuca | D95: AZ | E95: Tucson (Sierra Vista), AZ | G95: Army | H95: Web & Email | I95: Web Ad | K95: Your ad will appear on the installation MWR / FSS website. | L95: 12 | P95: 1500 | R95: =IF(ISNUMBER(M95),ROUND(M95/(1-Settings!$B$2)/Settings!$B$3,0)*Settings!$B$3,"") | S95: =IF(ISNUMBER(N95),ROUND(N95/(1-Settings!$B$2)/Settings!$B$3,0)*Settings!$B$3,"") | T95: =IF(ISNUMBER(O95),ROUND(O95/(1-Settings!$B$2)/Settings!$B$3,0)*Settings!$B$3,"") | U95: =IF(ISNUMBER(P95),ROUND(P95/(1-Settings!$B$2)/Settings!$B$3,0)*Settings!$B$3,"") | V95: =IF(ISNUMBER(Q95),ROUND(Q95/(1-Settings!$B$2)/Settings!$B$3,0)*Settings!$B$3,"") | W95: 4139 | X95: 5163 | Y95: 2026 | Z95: 2026-06 | AA95: Sold annually; Magazine printed quarterly | AC95: Military - National Publication Inventory Master_June 2026.xlsx | AD95: 2026_Rate_Card.pdf | AE95: Open in Box | AF95: Open in Box
A96: AZ-FORTNOVO-001 | B96: Fort Novosel | C96: Fort Rucker | D96: AZ | E96: Montgomery | F96: 36322 | G96: Army | H96: Print & Publications | I96: Restaurant & Entertainment Guide | J96: Full Page | K96: Your ad will appear in the Restaurant & Entertainment Guide. This is one of the only opportunities for off post restaurants and entertainment facilities to advertise on Fort Novosel. Distributed at the Newcomer's Welcome Briefing and inside multiple MWR facilities throughout the year. | L96: 12 | P96: 1800 | Q96: 0 | R96: =IF(ISNUMBER(M96),ROUND(M96/(1-Settings!$B$2)/Settings!$B$3,0)*Settings!$B$3,"") | S96: =IF(ISNUMBER(N96),ROUND(N96/(1-Settings!$B$2)/Settings!$B$3,0)*Settings!$B$3,"") | T96: =IF(ISNUMBER(O96),ROUND(O96/(1-Settings!$B$2)/Settings!$B$3,0)*Settings!$B$3,"") | U96: =IF(ISNUMBER(P96),ROUND(P96/(1-Settings!$B$2)/Settings!$B$3,0)*Settings!$B$3,"") | V96: =IF(ISNUMBER(Q96),ROUND(Q96/(1-Settings!$B$2)/Settings!$B$3,0)*Settings!$B$3,"") | W96: 3860 | X96: 5945 | AC96: MasterMilitaryOnBaseList 12.2.25 NS.xlsx | AD96: Gate Marquees - Rucker_Specs.docx | AE96: Open in Box | AF96: Open in Box
A97: AZ-LUKEAFB-001 | B97: Luke AFB | D97: AZ | E97: Phoenix (Prescott) | F97: 85309 | G97: Air Force | H97: Digital | I97: Base Theatre Preview | J97: 1920pxW x1080pxH | K97: Your ad will appear as a Base Theatre Preview | L97: 1 | M97: 200 | N97: 150 | O97: 100 | P97: 200 | Q97: 0 | R97: =IF(ISNUMBER(M97),ROUND(M97/(1-Settings!$B$2)/Settings!$B$3,0)*Settings!$B$3,"") | S97: =IF(ISNUMBER(N97),ROUND(N97/(1-Settings!$B$2)/Settings!$B$3,0)*Settings!$B$3,"") | T97: =IF(ISNUMBER(O97),ROUND(O97/(1-Settings!$B$2)/Settings!$B$3,0)*Settings!$B$3,"") | U97: =IF(ISNUMBER(P97),ROUND(P97/(1-Settings!$B$2)/Settings!$B$3,0)*Settings!$B$3,"") | V97: =IF(ISNUMBER(Q97),ROUND(Q97/(1-Settings!$B$2)/Settings!$B$3,0)*Settings!$B$3,"") | W97: 4607 | X97: 5689 | AA97: Inventory master 6/2026 lists Movie Theater Ad at $150 (1 mo) | AC97: MasterMilitaryOnBaseList 12.2.25 NS.xlsx | AD97: Luke Days 2026 - C Advertising & Exhibitors.pdf | AE97: Open in Box | AF97: Open in Box
A98: AZ-LUKEAFB-002 | B98: Luke AFB | D98: AZ | E98: Phoenix (Prescott) | F98: 85309 | G98: Air Force | H98: Digital | I98: Digital Monitors | J98: 12" tall x 21' wide (No Bleed) | K98: Your ad will appear on digtal monitors in Luke AFB facilities | L98: 1 | M98: 400 | N98: 350 | O98: 300 | P98: 600 | Q98: 0 | R98: =IF(ISNUMBER(M98),ROUND(M98/(1-Settings!$B$2)/Settings!$B$3,0)*Settings!$B$3,"") | S98: =IF(ISNUMBER(N98),ROUND(N98/(1-Settings!$B$2)/Settings!$B$3,0)*Settings!$B$3,"") | T98: =IF(ISNUMBER(O98),ROUND(O98/(1-Settings!$B$2)/Settings!$B$3,0)*Settings!$B$3,"") | U98: =IF(ISNUMBER(P98),ROUND(P98/(1-Settings!$B$2)/Settings!$B$3,0)*Settings!$B$3,"") | V98: =IF(ISNUMBER(Q98),ROUND(Q98/(1-Settings!$B$2)/Settings!$B$3,0)*Settings!$B$3,"") | W98: 4607 | X98: 5689 | AC98: MasterMilitaryOnBaseList 12.2.25 NS.xlsx | AD98: Luke Days 2026 - C Advertising & Exhibitors.pdf | AE98: Open in Box | AF98: Open in Box
A99: AZ-LUKEAFB-006 | B99: Luke AFB | D99: AZ | E99: Phoenix (Prescott) | F99: 85309 | G99: Air Force | H99: Print & Publications | I99: Magazine Ad - Back Cover | J99: 8"W x10.25"H (No Bleed), 8.5"W x11"H (Bleed) | K99: Your ad will appear on the back cover of "The Bolt" Magazine. | L99: 1 | M99: 800 | R99: =IF(ISNUMBER(M99),ROUND(M99/(1-Settings!$B$2)/Settings!$B$3,0)*Settings!$B$3,"") | S99: =IF(ISNUMBER(N99),ROUND(N99/(1-Settings!$B$2)/Settings!$B$3,0)*Settings!$B$3,"") | T99: =IF(ISNUMBER(O99),ROUND(O99/(1-Settings!$B$2)/Settings!$B$3,0)*Settings!$B$3,"") | U99: =IF(ISNUMBER(P99),ROUND(P99/(1-Settings!$B$2)/Settings!$B$3,0)*Settings!$B$3,"") | V99: =IF(ISNUMBER(Q99),ROUND(Q99/(1-Settings!$B$2)/Settings!$B$3,0)*Settings!$B$3,"") | W99: 4607 | X99: 5689 | AC99: MasterMilitaryOnBaseList 12.2.25 NS.xlsx | AD99: Luke Days 2026 - C Advertising & Exhibitors.pdf | AE99: Open in Box | AF99: Open in Box
A100: AZ-LUKEAFB-007 | B100: Luke AFB | D100: AZ | E100: Phoenix (Prescott) | F100: 85309 | G100: Air Force | H100: Print & Publications | I100: Magazine Ad - Full Page | J100: 8"W x10.25"H (No Bleed), 8.5"W x11"H (Bleed) | K100: Your ad will appear as a full page inside "The Bolt" Magazine. | L100: 1 | M100: 650 | N100: 600 | O100: 550 | Q100: 0 | R100: =IF(ISNUMBER(M100),ROUND(M100/(1-Settings!$B$2)/Settings!$B$3,0)*Settings!$B$3,"") | S100: =IF(ISNUMBER(N100),ROUND(N100/(1-Settings!$B$2)/Settings!$B$3,0)*Settings!$B$3,"") | T100: =IF(ISNUMBER(O100),ROUND(O100/(1-Settings!$B$2)/Settings!$B$3,0)*Settings!$B$3,"") | U100: =IF(ISNUMBER(P100),ROUND(P100/(1-Settings!$B$2)/Settings!$B$3,0)*Settings!$B$3,"") | V100: =IF(ISNUMBER(Q100),ROUND(Q100/(1-Settings!$B$2)/Settings!$B$3,0)*Settings!$B$3,"") | W100: 4607 | X100: 5689 | AC100: MasterMilitaryOnBaseList 12.2.25 NS.xlsx | AD100: Luke Days 2026 - C Advertising & Exhibitors.pdf | AE100: Open in Box | AF100: Open in Box
...

Sheet Bases
A1: Base | B1: Also known as | C1: State | D1: DMA / Metro | E1: Zip | F1: Branch | G1: Media options | H1: Digital | I1: Standard Media | J1: Large Format | K1: Print & Pubs | L1: Web & Email | M1: Active Duty (ref.) | N1: Dependents (ref.) | O1: Rate card year(s) | P1: Rows needing review
A2: Eielson AFB | C2: AK | D2: Fairbanks | E2: 99702 | F2: Air Force | G2: 8 | H2: 2 | I2: 2 | J2: 0 | K2: 1 | L2: 2 | M2: 1958 | N2: 2424 | O2: 2026 | P2: 0
A3: Fort Greely | C3: AK | D3: Fairbanks, AK | F3: Army | G3: 2 | H3: 1 | I3: 0 | J3: 0 | K3: 0 | L3: 1 | O3: 2026 | P3: 0
A4: Fort Jonathan Wainwright | C4: AK | D4: Fairbanks, AK | F4: Army | G4: 2 | H4: 1 | I4: 0 | J4: 0 | K4: 0 | L4: 1 | M4: 6117 | N4: 6995 | O4: 2026 | P4: 0
A5: JBER - Elmendorf AFB | B5: Joint Base Elmendorf-Richardson | C5: AK | D5: Anchorage | E5: 99506 | F5: Air Force | G5: 19 | H5: 4 | I5: 4 | J5: 1 | K5: 5 | L5: 1 | M5: 5504 | N5: 7035 | O5: 2026 | P5: 0
A6: Fort Novosel | B6: Fort Rucker | C6: AL | D6: Montgomery | E6: 36323 | F6: Army | G6: 18 | H6: 5 | I6: 3 | J6: 1 | K6: 4 | L6: 4 | M6: 3860 | N6: 5945 | O6: 2026 | P6: 0
A7: Maxwell AFB (Incl. Gunter) | B7: Maxwell-Gunter AFB | C7: AL | D7: Montgomery-Selma | E7: 36112 | F7: Air Force | G7: 5 | H7: 3 | I7: 0 | J7: 0 | K7: 1 | L7: 1 | M7: 3012 | N7: 5336 | O7: 2026 | P7: 1
A8: Redstone Arsenal | C8: AL | D8: Huntsville-Decatur (Flor) | E8: 35898 | F8: Army | G8: 16 | H8: 5 | I8: 4 | J8: 3 | K8: 1 | L8: 2 | M8: 588 | N8: 1518 | O8: 2026 | P8: 0
A9: Little Rock AFB | C9: AR | D9: Little Rock-Pine Bluff | E9: 72099 | F9: Air Force | G9: 19 | H9: 6 | I9: 3 | J9: 7 | K9: 0 | L9: 2 | M9: 3536 | N9: 4572 | O9: 2026 | P9: 0
A10: Davis-Monthan Air Force Base | C10: AZ | D10: Tucson (Sierra Vista), AZ | F10: Air Force | G10: 3 | H10: 1 | I10: 0 | J10: 0 | K10: 1 | L10: 1 | M10: 5995 | N10: 6924 | O10: 2026 | P10: 0
A11: Fort Huachuca | C11: AZ | D11: Tucson (Sierra Vista), AZ | F11: Army | G11: 3 | H11: 1 | I11: 0 | J11: 0 | K11: 1 | L11: 1 | M11: 4139 | N11: 5163 | O11: 2026 | P11: 0
A12: Luke AFB | C12: AZ | D12: Phoenix (Prescott) | E12: 85309 | F12: Air Force | G12: 12 | H12: 2 | I12: 3 | J12: 0 | K12: 5 | L12: 1 | M12: 4607 | N12: 5689 | O12: 2026 | P12: 0
A13: Yuma MCAS | C13: AZ | D13: Yuma-El Centro | E13: 85369 | F13: Marine Corps | G13: 7 | H13: 4 | I13: 1 | J13: 0 | K13: 0 | L13: 2 | M13: 4946 | N13: 4702 | O13: 2026 | P13: 1
A14: 29 Palms MC Air/Ground Combat Center | C14: CA | D14: Los Angeles | E14: 92278 | F14: Marine Corps | G14: 21 | H14: 5 | I14: 1 | J14: 13 | K14: 1 | L14: 1 | O14: 2023 | P14: 20
A15: Beale AFB | C15: CA | D15: Sacramnto-Stkton-Modesto | E15: 95903 | F15: Air Force | G15: 10 | H15: 2 | I15: 4 | J15: 1 | K15: 1 | L15: 0 | P15: 3
A16: Camp Pendleton | C16: CA | D16: San Diego | F16: Marine Corps | G16: 22 | H16: 6 | I16: 2 | J16: 10 | K16: 2 | L16: 2 | M16: 39690 | N16: 31010 | O16: 2026 | P16: 4
A17: China Lake NAVWEAPCEN | B17: NAWS China Lake | C17: CA | D17: Los Angeles | E17: 93555 | F17: Navy | G17: 11 | H17: 1 | I17: 7 | J17: 1 | K17: 2 | L17: 0 | P17: 1
A18: Edwards AFB | C18: CA | D18: Los Angeles | E18: 93524 | F18: Air Force | G18: 13 | H18: 6 | I18: 4 | J18: 0 | K18: 3 | L18: 0 | P18: 1
A19: Fort Irwin | C19: CA | D19: Los Angeles | E19: 92310 | F19: Army | G19: 4 | H19: 2 | I19: 1 | J19: 1 | K19: 0 | L19: 0 | P19: 2
A20: Lemoore NAS | C20: CA | D20: Fresno-Visalia | E20: 93246 | F20: Navy | G20: 26 | H20: 4 | I20: 12 | J20: 10 | K20: 0 | L20: 0 | P20: 0
A21: Los Angeles AFB | C21: CA | D21: Los Angeles | E21: 90245 | F21: Air Force | G21: 11 | H21: 4 | I21: 2 | J21: 1 | K21: 1 | L21: 3 | P21: 1
A22: MCAS Miramar | C22: CA | D22: San Diego | E22: 92145 | F22: Marine Corps | G22: 7 | H22: 2 | I22: 1 | J22: 1 | K22: 0 | L22: 3 | M22: 7535 | N22: 7007 | O22: 2026 | P22: 1
A23: NBVC Port Hueneme NCBC | B23: Naval Base Ventura County | C23: CA | D23: Los Angeles | E23: 93043 | F23: Navy | G23: 62 | H23: 14 | I23: 3 | J23: 43 | K23: 0 | L23: 0 | P23: 1
A24: Point Loma | B24: Naval Base Point Loma (San Diego) | C24: CA | D24: San Diego | E24: 92106 | F24: Navy | G24: 6 | H24: 3 | I24: 0 | J24: 0 | K24: 0 | L24: 3 | M24: 32983 | N24: 33574 | O24: 2026 | P24: 1
A25: Travis AFB | C25: CA | D25: Sacramnto-Stkton-Modesto | E25: 94535 | F25: Air Force | G25: 12 | H25: 4 | I25: 3 | J25: 0 | K25: 3 | L25: 2 | M25: 6675 | N25: 7960 | O25: 2020 | P25: 1
A26: Buckley AFB | C26: CO | D26: Denver | E26: 80011 | F26: Air Force | G26: 5 | H26: 3 | I26: 0 | J26: 0 | K26: 1 | L26: 1 | M26: 2540 | N26: 3106 | O26: 2026 | P26: 0
A27: Fort Carson | C27: CO | D27: Colorado Springs-Pueblo | E27: 80913 | F27: Army | G27: 39 | H27: 10 | I27: 7 | J27: 9 | K27: 8 | L27: 2 | M27: 24520 | N27: 32953 | O27: 2026 | P27: 12
A28: Peterson AFB | C28: CO | D28: Colorado Springs-Pueblo | E28: 80914 | F28: Air Force | G28: 8 | H28: 2 | I28: 0 | J28: 5 | K28: 0 | L28: 1 | M28: 3645 | N28: 6210 | O28: 2026 | P28: 2
A29: Schriever AFB | C29: CO | D29: Colorado Springs-Pueblo | E29: 80912 | F29: Air Force | G29: 5 | H29: 1 | I29: 1 | J29: 1 | K29: 1 | L29: 1 | M29: 1853 | N29: 2679 | O29: 2026 | P29: 1
A30: USAF Academy | C30: CO | D30: Colorado Springs-Pueblo | E30: 80840 | F30: Air Force | G30: 12 | H30: 2 | I30: 1 | J30: 0 | K30: 7 | L30: 2 | M30: 2070 | N30: 3209 | O30: 2026 | P30: 2
A31: New London NAVSUBBASE (Groton) | C31: CT | D31: Hartford-New Haven, CT | F31: Navy | G31: 3 | H31: 2 | I31: 0 | J31: 0 | K31: 0 | L31: 1 | M31: 6385 | N31: 7471 | O31: 2026 | P31: 0
A32: JBAB Anacostia NS | B32: JB Anacostia-Bolling | C32: DC | D32: Washington, DC (Hagrstwn) | E32: 20332 | F32: Navy | G32: 8 | H32: 1 | I32: 2 | J32: 1 | K32: 0 | L32: 4 | M32: 2491 | N32: 3654 | O32: 2026 | P32: 0
A33: Washington NAVDIST HQ | B33: Naval District Washington / Washington Navy Yard | C33: DC | D33: Washington, DC (Hagrstwn) | E33: 20374 | F33: Navy | G33: 11 | H33: 5 | I33: 2 | J33: 1 | K33: 0 | L33: 3 | M33: 3100 | N33: 5435 | O33: 2026 | P33: 0
A34: Dover AFB | C34: DE | D34: Philadelphia | E34: 19902 | F34: Air Force | G34: 12 | H34: 3 | I34: 4 | J34: 2 | K34: 0 | L34: 1 | M34: 3484 | N34: 4234 | O34: 2026 | P34: 11
A35: Eglin AFB | C35: FL | D35: Mobile-Pensacola (Ft Walt) | E35: 32542 | F35: Air Force | G35: 18 | H35: 1 | I35: 7 | J35: 5 | K35: 4 | L35: 1 | M35: 9243 | N35: 12793 | O35: 2026 | P35: 5
A36: Homestead AFB | C36: FL | D36: Miami-Ft. Lauderdale | E36: 33039 | F36: Air Force | G36: 1 | H36: 0 | I36: 0 | J36: 0 | K36: 0 | L36: 0 | M36: 429 | N36: 718 | P36: 1
A37: Hurlburt Field | C37: FL | D37: Mobile-Pensacola (Ft Walt) | E37: 32544 | F37: Air Force | G37: 10 | H37: 2 | I37: 4 | J37: 1 | K37: 2 | L37: 1 | M37: 8185 | N37: 10597 | O37: 2026 | P37: 0
A38: Jacksonville NAS | C38: FL | D38: Jacksonville | E38: 32212 | F38: Navy | G38: 14 | H38: 2 | I38: 4 | J38: 4 | K38: 2 | L38: 2 | M38: 6967 | N38: 9499 | O38: 2026 | P38: 0
A39: Key West NAS | C39: FL | D39: Miami-Ft. Lauderdale | E39: 33040 | F39: Navy | G39: 11 | H39: 3 | I39: 3 | J39: 2 | K39: 1 | L39: 2 | M39: 797 | N39: 986 | O39: 2026 | P39: 0
A40: MacDill AFB | C40: FL | D40: Tampa-St. Pete (Sarasota) | E40: 33621 | F40: Air Force | G40: 6 | H40: 3 | I40: 2 | J40: 0 | K40: 0 | L40: 1 | M40: 5705 | N40: 10061 | O40: 2026 | P40: 0
A41: Mayport NAVSTA | C41: FL | D41: Jacksonville | E41: 32228 | F41: Navy | G41: 16 | H41: 3 | I41: 3 | J41: 4 | K41: 4 | L41: 2 | M41: 10442 | N41: 14571 | O41: 2026 | P41: 1
A42: NOTU Cape Cape Canaveral | B42: NOTU Cape Canaveral | C42: FL | D42: Orlando-Daytona Bch-Melbrn | E42: 32920 | F42: Navy | G42: 8 | H42: 1 | I42: 2 | J42: 2 | K42: 1 | L42: 2 | M42: 163 | N42: 340 | O42: 2026 | P42: 0
A43: Nav Coastal Systems Ctr Panama City NSA | B43: NSA Panama City | C43: FL | D43: Panama City | E43: 32407 | F43: Navy | G43: 10 | H43: 1 | I43: 3 | J43: 3 | K43: 2 | L43: 1 | M43: 615 | N43: 615 | O43: 2026 | P43: 0
A44: Patrick AFB | C44: FL | D44: Orlando-Daytona Bch-Melbrn | E44: 32925 | F44: Air Force | G44: 11 | H44: 1 | I44: 3 | J44: 1 | K44: 5 | L44: 1 | M44: 1733 | N44: 2550 | O44: 2026 | P44: 0
A45: Pensacola NAS | C45: FL | D45: Mobile-Pensacola (Ft Walton) | E45: 32508 | F45: Navy | G45: 15 | H45: 5 | I45: 5 | J45: 2 | K45: 1 | L45: 2 | M45: 8595 | N45: 6512 | O45: 2026 | P45: 0
A46: Tyndall AFB | C46: FL | D46: Panama City | E46: 32403 | F46: Air Force | G46: 4 | H46: 1 | I46: 3 | J46: 0 | K46: 0 | L46: 0 | M46: 1633 | N46: 2089 | P46: 0
A47: US Army Garrison Miami Southern Command | C47: FL | D47: Miami-Ft. Lauderdale | F47: Air Force | G47: 2 | H47: 0 | I47: 0 | J47: 0 | K47: 0 | L47: 2 | M47: 1370 | N47: 2226 | O47: 2022 | P47: 0
A48: Whiting Field NAS | C48: FL | D48: Mobile-Pensacola (Ft Walt) | E48: 32570 | F48: Navy | G48: 10 | H48: 1 | I48: 3 | J48: 3 | K48: 2 | L48: 1 | M48: 1145 | N48: 1022 | O48: 2026 | P48: 0
A49: Albany MCLB | C49: GA | D49: Albany, GA | F49: Marine Corps | G49: 3 | H49: 2 | I49: 0 | J49: 0 | K49: 0 | L49: 1 | M49: 318 | N49: 571 | O49: 2026 | P49: 0
A50: Dobbins ARB | C50: GA | F50: Air Force | G50: 2 | H50: 1 | I50: 0 | J50: 0 | K50: 0 | L50: 1 | O50: 2026 | P50: 0
A51: Fort Benning | C51: GA | D51: Columbus, GA | F51: Army | G51: 3 | H51: 2 | I51: 0 | J51: 0 | K51: 0 | L51: 1 | M51: 24305 | N51: 22480 | O51: 2026 | P51: 0
A52: Fort Eisenhower | B52: Fort Gordon | C52: GA | D52: Augusta | E52: 30905 | F52: Army | G52: 29 | H52: 14 | I52: 5 | J52: 2 | K52: 0 | L52: 8 | M52: 11220 | N52: 14416 | O52: 2026 | P52: 7
A53: Fort Stewart / Hunter Army Airfield | B53: Fort Stewart | C53: GA | D53: Savannah | E53: 31314 | F53: Army | G53: 11 | H53: 4 | I53: 2 | J53: 3 | K53: 0 | L53: 1 | M53: 19476 | N53: 25826 | O53: 2026 | P53: 1
A54: Kings Bay NAVSUBBASE | C54: GA | D54: Jacksonville | E54: 31547 | F54: Navy | G54: 15 | H54: 5 | I54: 6 | J54: 1 | K54: 1 | L54: 2 | M54: 2918 | N54: 3953 | O54: 2026 | P54: 0
A55: Moody AFB | C55: GA | D55: Tallahassee-Thomasville | E55: 31699 | F55: Air Force | G55: 12 | H55: 6 | I55: 3 | J55: 0 | K55: 0 | L55: 3 | M55: 4562 | N55: 5322 | O55: 2026 | P55: 0
A56: Robins AFB | C56: GA | D56: Macon | E56: 31098 | F56: Air Force | G56: 5 | H56: 1 | I56: 2 | J56: 0 | K56: 1 | L56: 1 | M56: 3313 | N56: 4707 | O56: 2026 | P56: 1
A57: Fort Shafter | C57: HI | D57: Honolulu, HI | F57: Army | G57: 1 | H57: 0 | I57: 0 | J57: 0 | K57: 1 | L57: 0 | M57: 2584 | N57: 4653 | O57: 2026 | P57: 0
A58: Hickam AFB | B58: JB Pearl Harbor-Hickam | C58: HI | D58: Honolulu | E58: 96860 | F58: Air Force | G58: 5 | H58: 2 | I58: 1 | J58: 1 | K58: 0 | L58: 0 | M58: 5561 | N58: 7473 | P58: 0
A59: MCB Hawaii | B59: Kaneohe Bay | C59: HI | D59: Honolulu | E59: 96861 | F59: Marine Corps | G59: 9 | H59: 4 | I59: 3 | J59: 1 | K59: 0 | L59: 1 | M59: 9157 | N59: 7201 | P59: 3
A60: Pacific Missile Range Facilty (Barking Sands) | C60: HI | D60: Honolulu | E60: 96725 | F60: Navy | G60: 1 | H60: 1 | I60: 0 | J60: 0 | K60: 0 | L60: 0 | P60: 0
A61: Pearl Harbor NS | B61: JB Pearl Harbor-Hickam | C61: HI | D61: Honolulu | E61: 96860 | F61: Navy | G61: 7 | H61: 3 | I61: 1 | J61: 1 | K61: 0 | L61: 1 | M61: 5561 | N61: 7473 | O61: 2026 | P61: 0
A62: USAG Hawaii | B62: Schofield Barracks / Fort Shafter / Wheeler AAF | C62: HI | D62: Honolulu | E62: 96815 | F62: Army | G62: 26 | H62: 7 | I62: 12 | J62: 0 | K62: 5 | L62: 2 | M62: 15057 | N62: 18965 | O62: 2026 | P62: 0
A63: Wheeler Army Airfield | C63: HI | D63: Honolulu, HI | F63: Army | G63: 1 | H63: 0 | I63: 0 | J63: 0 | K63: 1 | L63: 0 | O63: 2026 | P63: 0
A64: Mountain Home AFB | C64: ID | D64: Boise | E64: 83648 | F64: Air Force | G64: 29 | H64: 7 | I64: 5 | J64: 0 | K64: 8 | L64: 1 | M64: 3387 | N64: 3784 | O64: 2026 | P64: 4
A65: Naval Station Great Lakes | C65: IL | D65: Chicago | F65: Navy | G65: 3 | H65: 0 | I65: 0 | J65: 0 | K65: 1 | L65: 2 | M65: 15726 | N65: 6149 | O65: 2026 | P65: 0
A66: Scott AFB | C66: IL | D66: St. Louis | E66: 62225 | F66: Air Force | G66: 13 | H66: 3 | I66: 3 | J66: 1 | K66: 4 | L66: 1 | M66: 4610 | N66: 7686 | O66: 2026 | P66: 0
A67: Crane Naval Support Activity | C67: IN | D67: Terre Haute | E67: 47522 | F67: Navy | G67: 8 | H67: 1 | I67: 5 | J67: 1 | K67: 0 | L67: 1 | M67: 3600 | O67: 2026 | P67: 0
A68: Fort Leavenworth | C68: KS | D68: Kansas City | E68: 66027 | F68: Army | G68: 26 | H68: 5 | I68: 3 | J68: 2 | K68: 6 | L68: 3 | M68: 3438 | N68: 7470 | O68: 2026 | P68: 4
A69: Fort Riley | C69: KS | D69: Topeka | F69: Army | G69: 67 | H69: 8 | I69: 17 | J69: 36 | K69: 3 | L69: 2 | M69: 15214 | N69: 18081 | O69: 2026 | P69: 1
A70: McConnell AFB | C70: KS | D70: Wichita-Hutchinson Plus | E70: 67221 | F70: Air Force | G70: 7 | H70: 2 | I70: 2 | J70: 0 | K70: 1 | L70: 2 | M70: 2899 | N70: 3577 | O70: 2026 | P70: 0
A71: Fort Knox | C71: KY | D71: Louisville | E71: 40121 | F71: Army | G71: 33 | H71: 9 | I71: 12 | J71: 8 | K71: 0 | L71: 2 | M71: 4842 | N71: 7088 | O71: 2026 | P71: 8
A72: Fort Campbell | C72: KY/TN | D72: Nashville | E72: 42223 | F72: Army | G72: 26 | H72: 5 | I72: 10 | J72: 6 | K72: 2 | L72: 2 | M72: 26824 | N72: 36153 | O72: 2026 | P72: 9
A73: Barksdale AFB | C73: LA | D73: Shreveport, LA | F73: Air Force | G73: 2 | H73: 1 | I73: 0 | J73: 0 | K73: 0 | L73: 1 | M73: 5175 | N73: 6715 | O73: 2026 | P73: 0
A74: Fort Johnson | B74: Fort Polk | C74: LA | D74: Alexandria, La | E74: 71459 | F74: Army | G74: 10 | H74: 2 | I74: 4 | J74: 2 | K74: 1 | L74: 1 | M74: 7783 | N74: 9601 | O74: 2026 | P74: 0
A75: New Orleans NAS JRB | C75: LA | D75: New Orleans | E75: 70143 | F75: Navy | G75: 9 | H75: 3 | I75: 3 | J75: 1 | K75: 1 | L75: 1 | M75: 463 | N75: 1132 | O75: 2026 | P75: 0
A76: Hanscom AFB | C76: MA | D76: Boston (Manchester) | E76: 1731 | F76: Air Force | G76: 8 | H76: 3 | I76: 3 | J76: 0 | K76: 1 | L76: 1 | M76: 833 | N76: 1124 | O76: 2026 | P76: 3
A77: Westover ARB | C77: MA | D77: Springfield-Holyoke, MA | F77: Air Force | G77: 3 | H77: 2 | I77: 0 | J77: 0 | K77: 0 | L77: 1 | M77: 168 | N77: 247 | O77: 2026 | P77: 0
A78: Aberdeen Proving Ground/ Edgewood Area | B78: APG | C78: MD | D78: Baltimore | E78: 21005 | F78: Army | G78: 28 | H78: 2 | I78: 5 | J78: 3 | K78: 17 | L78: 0 | M78: 831 | N78: 1841 | O78: 2024, 2026 | P78: 27
A79: Andrews Air Force Base | C79: MD | D79: Washington, DC | F79: Air Force | G79: 4 | H79: 1 | I79: 0 | J79: 0 | K79: 1 | L79: 2 | M79: 4312 | N79: 5760 | O79: 2026 | P79: 0
A80: Annapolis NS (Incl. USNA) | C80: MD | D80: Baltimore, MD | F80: Navy | G80: 4 | H80: 2 | I80: 0 | J80: 0 | K80: 0 | L80: 2 | M80: 1447 | N80: 1918 | O80: 2026 | P80: 0
A81: Detroit Arsenal | C81: MD | D81: Detroit | E81: 48092 | F81: Army | G81: 3 | H81: 0 | I81: 2 | J81: 0 | K81: 1 | L81: 0 | P81: 0
A82: Fort Detrick | C82: MD | D82: Washington, DC (Hagrstwn) | F82: Army | G82: 2 | H82: 0 | I82: 0 | J82: 0 | K82: 1 | L82: 1 | M82: 991 | N82: 1873 | O82: 2026 | P82: 0
A83: Fort George G. Meade | C83: MD | D83: Baltimore | F83: Army | G83: 12 | H83: 3 | I83: 4 | J83: 4 | K83: 0 | L83: 1 | M83: 11140 | N83: 14901 | O83: 2026 | P83: 0
A84: Indian Head NAV ORD STA | C84: MD | D84: Washington, DC (Hagrstwn) | F84: Navy | G84: 2 | H84: 0 | I84: 0 | J84: 0 | K84: 0 | L84: 2 | M84: 584 | N84: 620 | O84: 2026 | P84: 0
A85: Patuxent River NAS | C85: MD | D85: Washington, DC (Hagrstwn) | E85: 20670 | F85: Navy | G85: 10 | H85: 3 | I85: 3 | J85: 2 | K85: 0 | L85: 2 | M85: 2267 | N85: 4150 | O85: 2026 | P85: 0
A86: Walter Reed NNMC Bethesda | C86: MD | D86: Washington, DC (Hagrstwn) | F86: Navy | G86: 2 | H86: 0 | I86: 0 | J86: 0 | K86: 0 | L86: 2 | M86: 4322 | N86: 5945 | O86: 2026 | P86: 0
A87: Portsmouth Naval Shipyard | C87: ME/NH | D87: Boston, MA | F87: Navy | G87: 2 | H87: 1 | I87: 0 | J87: 0 | K87: 0 | L87: 1 | M87: 959 | N87: 1105 | O87: 2026 | P87: 0
A88: Fort Leonard Wood | C88: MO | D88: Springfield, Mo | E88: 65473 | F88: Army | G88: 37 | H88: 3 | I88: 21 | J88: 3 | K88: 5 | L88: 5 | M88: 12218 | N88: 11261 | O88: 2026 | P88: 4
A89: Whiteman AFB | C89: MO | D89: Kansas City | E89: 65305 | F89: Air Force | G89: 19 | H89: 7 | I89: 7 | J89: 2 | K89: 2 | L89: 1 | M89: 3831 | N89: 4381 | O89: 2026 | P89: 2
A90: Gulfport NCBC | C90: MS | D90: Biloxi-Gulfport | E90: 39501 | F90: Navy | G90: 11 | H90: 3 | I90: 2 | J90: 3 | K90: 1 | L90: 2 | M90: 2906 | N90: 3970 | O90: 2026 | P90: 0
A91: Keesler AFB | C91: MS | D91: Biloxi-Gulfport | E91: 39534 | F91: Air Force | G91: 21 | H91: 3 | I91: 2 | J91: 4 | K91: 8 | L91: 3 | M91: 5162 | N91: 4425 | O91: 2026 | P91: 0
A92: Meridian NAS | C92: MS | D92: Meridian | E92: 39309 | F92: Navy | G92: 11 | H92: 2 | I92: 2 | J92: 3 | K92: 2 | L92: 1 | M92: 1126 | N92: 680 | O92: 2026 | P92: 0
A93: Malmstrom AFB | C93: MT | D93: Great Falls | E93: 59402 | F93: Air Force | G93: 8 | H93: 1 | I93: 3 | J93: 2 | K93: 2 | L93: 0 | P93: 1
A94: Cherry Point MCAS | C94: NC | D94: Greenville-N.Bern-Washngtn | E94: 28533 | F94: Marine Corps | G94: 6 | H94: 1 | I94: 4 | J94: 0 | K94: 0 | L94: 1 | M94: 5973 | N94: 6547 | O94: 2026 | P94: 1
A95: Fort Liberty | B95: Fort Bragg | C95: NC | D95: Raleigh-Durham (Fayetvlle) | E95: 28307 | F95: Army | G95: 35 | H95: 3 | I95: 6 | J95: 21 | K95: 2 | L95: 2 | M95: 45055 | N95: 64046 | O95: 2026 | P95: 0
A96: New River MCAS | C96: NC | D96: Greenville-N.Bern-Washngtn | E96: 28545 | F96: Marine Corps | G96: 27 | H96: 9 | I96: 10 | J96: 3 | K96: 0 | L96: 3 | O96: 2026 | P96: 21
A97: Grand Forks AFB | C97: ND | D97: Fargo-Valley City, ND | F97: Air Force | G97: 2 | H97: 1 | I97: 0 | J97: 0 | K97: 0 | L97: 1 | M97: 1659 | N97: 1901 | O97: 2026 | P97: 0
A98: Minot AFB | C98: ND | D98: Minot-Bismarck-Dickinson, ND | F98: Air Force | G98: 3 | H98: 2 | I98: 0 | J98: 0 | K98: 0 | L98: 1 | M98: 5625 | N98: 5406 | O98: 2026 | P98: 0
A99: Earle NWS | C99: NJ | D99: New York, NY | F99: Navy | G99: 2 | H99: 0 | I99: 0 | J99: 0 | K99: 0 | L99: 2 | M99: 2000 | O99: 2026 | P99: 0
A100: Joint Base Lakehurst - McGuire - Dix | C100: NJ | D100: Trenton, NJ | F100: Joint Base | G100: 4 | H100: 1 | I100: 0 | J100: 0 | K100: 2 | L100: 1 | M100: 5701 | N100: 7607 | O100: 2026 | P100: 0
...

Sheet Change Log
A1: Date | B1: Who | C1: Base | D1: What changed | E1: Rate card / source used
A2: 2026-09-29 | B2: Claude (for Jon) | C2: All | D2: Initial standardized master built from MasterMilitaryOnBaseList 12.2.25 NS.xlsx; client prices converted to margin-driven formulas; categories assigned; review flags added. | E2: Box > Military > Master Grid
